[
  {
    "name": "Wanda Byers",
    "phone": "+1 (860) 411-2152",
    "city": "Lacomb",
    "address": "534 Lynch Street, Fannett, Louisiana, 9669",
    "enabled": true
  },
  {
    "name": "Fanny Weber",
    "phone": "+1 (898) 414-2987",
    "city": "Tolu",
    "address": "655 Kings Place, Vaughn, Arkansas, 4532",
    "enabled": true
  },
  {
    "name": "Evans Waller",
    "phone": "+1 (874) 501-2749",
    "city": "Crenshaw",
    "address": "531 Malta Street, Riner, Marshall Islands, 7262",
    "enabled": false
  },
  {
    "name": "Maude Young",
    "phone": "+1 (850) 421-3575",
    "city": "Ryderwood",
    "address": "409 Erskine Loop, Lafferty, New Mexico, 1461",
    "enabled": true
  },
  {
    "name": "Catalina Hays",
    "phone": "+1 (998) 409-2176",
    "city": "Epworth",
    "address": "416 Leonora Court, Chamizal, Virginia, 1019",
    "enabled": true
  },
  {
    "name": "Nieves Fowler",
    "phone": "+1 (918) 455-3623",
    "city": "Albrightsville",
    "address": "404 Cozine Avenue, Jackpot, Kentucky, 3747",
    "enabled": true
  },
  {
    "name": "Logan Gallegos",
    "phone": "+1 (969) 579-3893",
    "city": "Hackneyville",
    "address": "185 Rose Street, Ballico, Massachusetts, 5309",
    "enabled": false
  },
  {
    "name": "Violet Torres",
    "phone": "+1 (857) 592-2135",
    "city": "Hinsdale",
    "address": "419 Ferry Place, Waumandee, Iowa, 8035",
    "enabled": true
  },
  {
    "name": "Larsen Owen",
    "phone": "+1 (918) 410-2330",
    "city": "Warren",
    "address": "355 Doughty Street, Cucumber, Virgin Islands, 2975",
    "enabled": false
  },
  {
    "name": "Robert Calhoun",
    "phone": "+1 (955) 521-2335",
    "city": "Harold",
    "address": "260 Independence Avenue, Tyhee, Texas, 6361",
    "enabled": true
  },
  {
    "name": "Dina Mcclain",
    "phone": "+1 (829) 551-3845",
    "city": "Calpine",
    "address": "282 Roebling Street, Beaulieu, Wyoming, 5196",
    "enabled": true
  },
  {
    "name": "Erna Rivers",
    "phone": "+1 (924) 446-3699",
    "city": "Munjor",
    "address": "283 Poplar Avenue, Marenisco, North Dakota, 9099",
    "enabled": false
  },
  {
    "name": "Jaclyn Bright",
    "phone": "+1 (883) 440-3754",
    "city": "Emory",
    "address": "595 Oriental Boulevard, Belfair, Minnesota, 8938",
    "enabled": false
  },
  {
    "name": "Banks Banks",
    "phone": "+1 (902) 456-3471",
    "city": "Onton",
    "address": "670 Stoddard Place, Williams, Connecticut, 3591",
    "enabled": true
  },
  {
    "name": "Whitaker Kerr",
    "phone": "+1 (949) 404-2631",
    "city": "Sena",
    "address": "279 Losee Terrace, Celeryville, Oklahoma, 1984",
    "enabled": true
  },
  {
    "name": "Bianca Newman",
    "phone": "+1 (925) 530-2806",
    "city": "Brandywine",
    "address": "902 Brighton Court, Drytown, District Of Columbia, 7533",
    "enabled": true
  },
  {
    "name": "Carey Jordan",
    "phone": "+1 (858) 586-3043",
    "city": "Sutton",
    "address": "681 Cove Lane, Brady, Kansas, 7031",
    "enabled": true
  },
  {
    "name": "Moody Adkins",
    "phone": "+1 (936) 474-2682",
    "city": "Martinsville",
    "address": "406 Scott Avenue, Dotsero, Vermont, 9571",
    "enabled": false
  },
  {
    "name": "Paige Fitzgerald",
    "phone": "+1 (939) 537-2279",
    "city": "Bagtown",
    "address": "622 Clarkson Avenue, Eden, Maine, 2809",
    "enabled": true
  },
  {
    "name": "Pansy Diaz",
    "phone": "+1 (959) 411-3569",
    "city": "Sunwest",
    "address": "865 Kingsway Place, Tuskahoma, Oregon, 3299",
    "enabled": true
  },
  {
    "name": "Lang Olson",
    "phone": "+1 (860) 545-2681",
    "city": "Nettie",
    "address": "704 Boardwalk , Dunnavant, Georgia, 7635",
    "enabled": false
  },
  {
    "name": "Sandoval Pierce",
    "phone": "+1 (975) 511-3099",
    "city": "Carlton",
    "address": "801 Verona Place, Tampico, Alaska, 5405",
    "enabled": false
  },
  {
    "name": "Leticia Sosa",
    "phone": "+1 (947) 462-2298",
    "city": "Wikieup",
    "address": "535 Franklin Avenue, Wheatfields, New Jersey, 6810",
    "enabled": false
  },
  {
    "name": "Stephenson Guzman",
    "phone": "+1 (873) 417-2905",
    "city": "Ruckersville",
    "address": "109 Opal Court, Blanco, Rhode Island, 3197",
    "enabled": false
  },
  {
    "name": "Billie Sims",
    "phone": "+1 (950) 574-3153",
    "city": "Otranto",
    "address": "911 Williams Place, Salix, Federated States Of Micronesia, 6231",
    "enabled": true
  },
  {
    "name": "Jo Whitaker",
    "phone": "+1 (865) 538-2664",
    "city": "Hayden",
    "address": "580 Johnson Avenue, Witmer, Alabama, 3672",
    "enabled": false
  },
  {
    "name": "Melton Allen",
    "phone": "+1 (909) 456-2314",
    "city": "Greenbackville",
    "address": "476 Sheffield Avenue, Detroit, Puerto Rico, 7901",
    "enabled": true
  },
  {
    "name": "Deanna Hardin",
    "phone": "+1 (835) 482-2474",
    "city": "Abiquiu",
    "address": "448 Sunnyside Court, Cresaptown, Michigan, 6637",
    "enabled": false
  },
  {
    "name": "Ruthie Cline",
    "phone": "+1 (990) 520-2159",
    "city": "Turpin",
    "address": "475 Bush Street, Faywood, American Samoa, 4972",
    "enabled": false
  },
  {
    "name": "Robbie Waters",
    "phone": "+1 (869) 554-3821",
    "city": "Elrama",
    "address": "895 Hinsdale Street, Wedgewood, Illinois, 2312",
    "enabled": false
  },
  {
    "name": "Frye Farmer",
    "phone": "+1 (996) 572-3652",
    "city": "Colton",
    "address": "720 Anchorage Place, Derwood, Colorado, 4371",
    "enabled": true
  },
  {
    "name": "Staci Benton",
    "phone": "+1 (858) 491-3967",
    "city": "Sexton",
    "address": "152 Ridgecrest Terrace, Bangor, Northern Mariana Islands, 4080",
    "enabled": false
  },
  {
    "name": "Sargent Huff",
    "phone": "+1 (958) 427-3951",
    "city": "Spokane",
    "address": "757 Jaffray Street, Odessa, Montana, 3730",
    "enabled": false
  },
  {
    "name": "Ruth Davidson",
    "phone": "+1 (809) 475-2939",
    "city": "Grahamtown",
    "address": "760 River Street, Alafaya, Utah, 9494",
    "enabled": true
  },
  {
    "name": "Ward Skinner",
    "phone": "+1 (858) 440-2330",
    "city": "Greenock",
    "address": "418 Middagh Street, Highland, Guam, 734",
    "enabled": false
  },
  {
    "name": "Kara Clemons",
    "phone": "+1 (847) 418-2411",
    "city": "Kersey",
    "address": "709 Emerson Place, Grapeview, Tennessee, 6265",
    "enabled": true
  },
  {
    "name": "Blair Bowman",
    "phone": "+1 (824) 438-3744",
    "city": "Ona",
    "address": "956 Commercial Street, Roderfield, Nevada, 5617",
    "enabled": true
  },
  {
    "name": "Susanna Armstrong",
    "phone": "+1 (837) 526-2784",
    "city": "Rossmore",
    "address": "219 Cumberland Walk, Guthrie, Indiana, 2988",
    "enabled": true
  },
  {
    "name": "Ericka Bullock",
    "phone": "+1 (861) 430-3482",
    "city": "Summerset",
    "address": "644 Gunther Place, Fidelis, New Hampshire, 5887",
    "enabled": false
  },
  {
    "name": "Rodriquez Walsh",
    "phone": "+1 (935) 442-3071",
    "city": "Oasis",
    "address": "951 Ocean Avenue, Bowmansville, West Virginia, 5609",
    "enabled": true
  },
  {
    "name": "Lori Levy",
    "phone": "+1 (906) 553-2190",
    "city": "Remington",
    "address": "814 Holt Court, Elbert, Wisconsin, 5137",
    "enabled": false
  },
  {
    "name": "Lopez Weiss",
    "phone": "+1 (916) 587-3768",
    "city": "Lodoga",
    "address": "370 Cypress Court, Norfolk, New York, 5522",
    "enabled": true
  },
  {
    "name": "Nguyen Osborne",
    "phone": "+1 (966) 497-3487",
    "city": "Independence",
    "address": "826 Ditmars Street, Wright, California, 7131",
    "enabled": false
  },
  {
    "name": "Gloria Taylor",
    "phone": "+1 (986) 433-2533",
    "city": "Trail",
    "address": "815 Summit Street, Belmont, Palau, 6066",
    "enabled": false
  },
  {
    "name": "Beverley Rodgers",
    "phone": "+1 (965) 464-3955",
    "city": "Madaket",
    "address": "706 Nichols Avenue, Kidder, Idaho, 1479",
    "enabled": true
  },
  {
    "name": "Faye Myers",
    "phone": "+1 (864) 562-3351",
    "city": "Katonah",
    "address": "509 Myrtle Avenue, Neibert, Florida, 4653",
    "enabled": false
  },
  {
    "name": "Socorro Poole",
    "phone": "+1 (957) 481-2547",
    "city": "Enoree",
    "address": "203 Dewey Place, Martell, Mississippi, 8207",
    "enabled": true
  },
  {
    "name": "Mccray Berger",
    "phone": "+1 (889) 541-3166",
    "city": "Chapin",
    "address": "957 Atlantic Avenue, Deltaville, North Carolina, 7706",
    "enabled": false
  },
  {
    "name": "Cathy Hampton",
    "phone": "+1 (969) 437-3983",
    "city": "Bayview",
    "address": "174 Ovington Avenue, Nogal, Maryland, 2811",
    "enabled": true
  },
  {
    "name": "Saunders Levine",
    "phone": "+1 (931) 578-3115",
    "city": "Adamstown",
    "address": "749 Strickland Avenue, Lowell, Washington, 3926",
    "enabled": true
  },
  {
    "name": "Audrey Perry",
    "phone": "+1 (975) 496-3490",
    "city": "Cressey",
    "address": "117 Lenox Road, Roland, Arizona, 3181",
    "enabled": false
  },
  {
    "name": "Christie Cannon",
    "phone": "+1 (865) 445-3182",
    "city": "Brooktrails",
    "address": "587 Emerald Street, Hendersonville, Hawaii, 5271",
    "enabled": false
  },
  {
    "name": "Bartlett Bauer",
    "phone": "+1 (826) 436-3746",
    "city": "Lloyd",
    "address": "945 Strong Place, Durham, Ohio, 5504",
    "enabled": true
  },
  {
    "name": "Daugherty Winters",
    "phone": "+1 (829) 583-2544",
    "city": "Kirk",
    "address": "473 Kane Place, Nescatunga, South Carolina, 4427",
    "enabled": true
  },
  {
    "name": "Gaines Mckee",
    "phone": "+1 (923) 430-3825",
    "city": "Fairfield",
    "address": "648 Bay Street, Mansfield, South Dakota, 3716",
    "enabled": false
  },
  {
    "name": "Helene Williams",
    "phone": "+1 (992) 519-2400",
    "city": "Osmond",
    "address": "241 Columbus Place, Rockingham, Delaware, 3995",
    "enabled": false
  },
  {
    "name": "Ana Hurley",
    "phone": "+1 (888) 404-2289",
    "city": "Croom",
    "address": "781 Arkansas Drive, Ventress, Nebraska, 6995",
    "enabled": true
  },
  {
    "name": "Edith Contreras",
    "phone": "+1 (923) 514-2046",
    "city": "Herlong",
    "address": "581 Lester Court, Yardville, Pennsylvania, 3012",
    "enabled": true
  },
  {
    "name": "Graves Ortiz",
    "phone": "+1 (818) 491-3010",
    "city": "Ernstville",
    "address": "279 Gotham Avenue, Robinette, Louisiana, 4619",
    "enabled": false
  },
  {
    "name": "Carrie Hicks",
    "phone": "+1 (829) 474-3053",
    "city": "Takilma",
    "address": "583 Cambridge Place, Gilgo, Arkansas, 3911",
    "enabled": true
  },
  {
    "name": "Bass Duke",
    "phone": "+1 (906) 479-2170",
    "city": "Boonville",
    "address": "640 Dwight Street, Wyano, Marshall Islands, 1814",
    "enabled": true
  },
  {
    "name": "Jacobs Shields",
    "phone": "+1 (929) 589-3128",
    "city": "Allamuchy",
    "address": "959 Just Court, Barclay, New Mexico, 6787",
    "enabled": false
  },
  {
    "name": "Therese Rich",
    "phone": "+1 (817) 460-2756",
    "city": "Titanic",
    "address": "824 Wallabout Street, Sterling, Virginia, 2575",
    "enabled": false
  },
  {
    "name": "Rivera Hancock",
    "phone": "+1 (867) 593-2612",
    "city": "Barronett",
    "address": "944 Croton Loop, Orin, Kentucky, 1316",
    "enabled": true
  },
  {
    "name": "Shepard Estrada",
    "phone": "+1 (903) 478-2168",
    "city": "Carrizo",
    "address": "493 Grant Avenue, Yonah, Massachusetts, 225",
    "enabled": true
  },
  {
    "name": "Guthrie Lancaster",
    "phone": "+1 (848) 476-2561",
    "city": "Toftrees",
    "address": "150 Cherry Street, Frierson, Iowa, 5884",
    "enabled": true
  },
  {
    "name": "Chasity Leonard",
    "phone": "+1 (981) 492-2241",
    "city": "Cobbtown",
    "address": "978 Roosevelt Court, Harrodsburg, Virgin Islands, 4362",
    "enabled": false
  },
  {
    "name": "Gilda Hansen",
    "phone": "+1 (992) 482-2943",
    "city": "Bodega",
    "address": "381 Beayer Place, Marienthal, Texas, 2650",
    "enabled": false
  },
  {
    "name": "Powers Smith",
    "phone": "+1 (858) 582-2064",
    "city": "Harborton",
    "address": "428 Pierrepont Place, Hickory, Wyoming, 9130",
    "enabled": false
  },
  {
    "name": "Aileen Larson",
    "phone": "+1 (967) 533-2029",
    "city": "Chloride",
    "address": "899 Truxton Street, Coyote, North Dakota, 9163",
    "enabled": true
  },
  {
    "name": "Stewart Richards",
    "phone": "+1 (880) 536-3234",
    "city": "Waverly",
    "address": "367 Prospect Place, Romeville, Minnesota, 4885",
    "enabled": false
  },
  {
    "name": "Stokes Valenzuela",
    "phone": "+1 (923) 447-2407",
    "city": "Savage",
    "address": "612 Emmons Avenue, Muse, Connecticut, 4788",
    "enabled": false
  },
  {
    "name": "Jeannine Leach",
    "phone": "+1 (963) 555-3642",
    "city": "Dixie",
    "address": "140 Montgomery Place, Kingstowne, Oklahoma, 6131",
    "enabled": false
  },
  {
    "name": "Ernestine Rose",
    "phone": "+1 (975) 485-3163",
    "city": "Dahlen",
    "address": "351 Sutton Street, Sparkill, District Of Columbia, 9397",
    "enabled": true
  },
  {
    "name": "Addie Robbins",
    "phone": "+1 (907) 434-3746",
    "city": "Chilton",
    "address": "941 Manhattan Court, Brenton, Kansas, 4825",
    "enabled": true
  },
  {
    "name": "Craig Kinney",
    "phone": "+1 (888) 518-2831",
    "city": "Haring",
    "address": "693 Pleasant Place, Windsor, Vermont, 6774",
    "enabled": true
  },
  {
    "name": "Sherri Duncan",
    "phone": "+1 (919) 407-3134",
    "city": "Loma",
    "address": "353 Lyme Avenue, Sunnyside, Maine, 6450",
    "enabled": true
  },
  {
    "name": "Beard Downs",
    "phone": "+1 (808) 598-3243",
    "city": "Biddle",
    "address": "803 Doone Court, Whitestone, Oregon, 3513",
    "enabled": false
  },
  {
    "name": "Randi Cole",
    "phone": "+1 (991) 445-3793",
    "city": "Cascades",
    "address": "698 Cass Place, Breinigsville, Georgia, 6488",
    "enabled": false
  },
  {
    "name": "Gonzales Acosta",
    "phone": "+1 (902) 451-2808",
    "city": "Caln",
    "address": "774 Rutledge Street, Caberfae, Alaska, 4083",
    "enabled": true
  },
  {
    "name": "John Valdez",
    "phone": "+1 (949) 525-3114",
    "city": "Forestburg",
    "address": "633 Canarsie Road, Hall, New Jersey, 9791",
    "enabled": true
  },
  {
    "name": "Alana Trujillo",
    "phone": "+1 (886) 542-2135",
    "city": "Ferney",
    "address": "559 Nautilus Avenue, Buxton, Rhode Island, 6154",
    "enabled": true
  },
  {
    "name": "Mccall Alvarez",
    "phone": "+1 (912) 464-3913",
    "city": "Frizzleburg",
    "address": "127 Chester Court, Hardyville, Federated States Of Micronesia, 2844",
    "enabled": false
  },
  {
    "name": "Wallace Roberson",
    "phone": "+1 (959) 545-2989",
    "city": "Edmund",
    "address": "198 Clifton Place, Wakulla, Alabama, 8991",
    "enabled": false
  },
  {
    "name": "Beatrice Ball",
    "phone": "+1 (935) 533-2473",
    "city": "Falmouth",
    "address": "733 Ryder Street, Cannondale, Puerto Rico, 7309",
    "enabled": true
  },
  {
    "name": "Marshall Gaines",
    "phone": "+1 (908) 450-2138",
    "city": "Selma",
    "address": "383 Stillwell Avenue, Byrnedale, Michigan, 6362",
    "enabled": false
  },
  {
    "name": "Mcmillan Melendez",
    "phone": "+1 (984) 401-3831",
    "city": "Dennard",
    "address": "319 Preston Court, Lorraine, American Samoa, 7082",
    "enabled": false
  },
  {
    "name": "Andrea Jenkins",
    "phone": "+1 (900) 539-2692",
    "city": "Nutrioso",
    "address": "995 Maujer Street, Whitewater, Illinois, 8536",
    "enabled": true
  },
  {
    "name": "Jeanie Huber",
    "phone": "+1 (830) 489-3807",
    "city": "Walton",
    "address": "342 Rost Place, Tibbie, Colorado, 2442",
    "enabled": false
  },
  {
    "name": "Dickerson Shepard",
    "phone": "+1 (979) 472-3603",
    "city": "Torboy",
    "address": "287 Huron Street, Harviell, Northern Mariana Islands, 7457",
    "enabled": true
  },
  {
    "name": "Kinney Gutierrez",
    "phone": "+1 (976) 487-2628",
    "city": "Salunga",
    "address": "169 Wythe Avenue, Morgandale, Montana, 3136",
    "enabled": false
  },
  {
    "name": "Hernandez Craig",
    "phone": "+1 (922) 409-3033",
    "city": "Orick",
    "address": "255 Jefferson Street, Chamberino, Utah, 4500",
    "enabled": true
  },
  {
    "name": "Hines Ingram",
    "phone": "+1 (937) 486-2441",
    "city": "Turah",
    "address": "749 Hazel Court, Movico, Guam, 8977",
    "enabled": false
  },
  {
    "name": "Huber Haley",
    "phone": "+1 (848) 413-3488",
    "city": "Westwood",
    "address": "420 Miami Court, Jeff, Tennessee, 626",
    "enabled": false
  },
  {
    "name": "Elva Wiley",
    "phone": "+1 (951) 434-2379",
    "city": "Westphalia",
    "address": "525 Kane Street, Hessville, Nevada, 3763",
    "enabled": false
  },
  {
    "name": "Clarke Wagner",
    "phone": "+1 (874) 433-2019",
    "city": "Caledonia",
    "address": "762 Battery Avenue, Edgar, Indiana, 3272",
    "enabled": false
  },
  {
    "name": "Bertha Pratt",
    "phone": "+1 (895) 522-3645",
    "city": "Rutherford",
    "address": "616 Joval Court, Indio, New Hampshire, 3349",
    "enabled": false
  },
  {
    "name": "Casey Drake",
    "phone": "+1 (929) 503-2392",
    "city": "Bannock",
    "address": "324 Bay Avenue, Lawrence, West Virginia, 3269",
    "enabled": false
  },
  {
    "name": "Alyssa Franklin",
    "phone": "+1 (856) 554-2333",
    "city": "Mapletown",
    "address": "948 Fayette Street, Canterwood, Wisconsin, 2846",
    "enabled": true
  },
  {
    "name": "Alexandra Glass",
    "phone": "+1 (905) 434-2887",
    "city": "Rosburg",
    "address": "653 Gardner Avenue, Greensburg, New York, 9742",
    "enabled": true
  },
  {
    "name": "Amanda Mcgowan",
    "phone": "+1 (954) 478-3904",
    "city": "Falconaire",
    "address": "364 Norfolk Street, Smeltertown, California, 9832",
    "enabled": true
  },
  {
    "name": "Lucinda Pittman",
    "phone": "+1 (848) 534-2430",
    "city": "Sehili",
    "address": "687 Lloyd Court, Longbranch, Palau, 2735",
    "enabled": true
  },
  {
    "name": "Thelma Cantu",
    "phone": "+1 (845) 537-3511",
    "city": "Mooresburg",
    "address": "209 Bushwick Court, Bloomington, Idaho, 1113",
    "enabled": true
  },
  {
    "name": "Jeannette Hinton",
    "phone": "+1 (912) 512-2967",
    "city": "Morriston",
    "address": "317 Centre Street, Riegelwood, Florida, 4869",
    "enabled": false
  },
  {
    "name": "Susie Dyer",
    "phone": "+1 (984) 424-2441",
    "city": "Emison",
    "address": "634 Bridgewater Street, Greer, Mississippi, 3253",
    "enabled": true
  },
  {
    "name": "Coffey Ballard",
    "phone": "+1 (939) 518-3945",
    "city": "Vivian",
    "address": "264 Melba Court, Loretto, North Carolina, 2211",
    "enabled": true
  },
  {
    "name": "Lorrie Hardy",
    "phone": "+1 (969) 519-2120",
    "city": "Oberlin",
    "address": "785 Morton Street, Coalmont, Maryland, 362",
    "enabled": false
  },
  {
    "name": "Chen Jennings",
    "phone": "+1 (827) 409-2068",
    "city": "Jacksonburg",
    "address": "466 Dewitt Avenue, Corriganville, Washington, 7594",
    "enabled": true
  },
  {
    "name": "Mcguire Austin",
    "phone": "+1 (916) 408-3558",
    "city": "Advance",
    "address": "517 Meadow Street, Websterville, Arizona, 5893",
    "enabled": true
  },
  {
    "name": "Jane Roman",
    "phone": "+1 (811) 599-3560",
    "city": "Wildwood",
    "address": "514 Jodie Court, Bridgetown, Hawaii, 9012",
    "enabled": false
  },
  {
    "name": "Fitzgerald Gardner",
    "phone": "+1 (967) 528-2421",
    "city": "Jenkinsville",
    "address": "330 Moultrie Street, Sugartown, Ohio, 5065",
    "enabled": false
  },
  {
    "name": "Keller Dillon",
    "phone": "+1 (941) 581-3110",
    "city": "Strong",
    "address": "798 Bliss Terrace, Gerton, South Carolina, 7030",
    "enabled": false
  },
  {
    "name": "Viola Deleon",
    "phone": "+1 (844) 571-2259",
    "city": "Cedarville",
    "address": "776 Everett Avenue, Townsend, South Dakota, 8929",
    "enabled": true
  },
  {
    "name": "Davidson Underwood",
    "phone": "+1 (872) 513-3787",
    "city": "Dargan",
    "address": "960 Fountain Avenue, Waterloo, Delaware, 2244",
    "enabled": true
  },
  {
    "name": "Miriam Foreman",
    "phone": "+1 (968) 439-3071",
    "city": "Saticoy",
    "address": "602 Hoyts Lane, Ada, Nebraska, 973",
    "enabled": false
  },
  {
    "name": "Sharlene Mullen",
    "phone": "+1 (814) 582-3307",
    "city": "Gasquet",
    "address": "368 Hoyt Street, Waterford, Pennsylvania, 2008",
    "enabled": false
  },
  {
    "name": "Suzette Bond",
    "phone": "+1 (965) 555-3972",
    "city": "Herald",
    "address": "788 Lincoln Avenue, Leeper, Louisiana, 2784",
    "enabled": true
  },
  {
    "name": "Kimberly Rowe",
    "phone": "+1 (865) 469-2692",
    "city": "Frystown",
    "address": "776 Livingston Street, Avalon, Arkansas, 6295",
    "enabled": false
  },
  {
    "name": "Hodges Little",
    "phone": "+1 (901) 600-3676",
    "city": "Delwood",
    "address": "325 Macon Street, Edgewater, Marshall Islands, 8071",
    "enabled": false
  },
  {
    "name": "Nettie Berry",
    "phone": "+1 (873) 536-2854",
    "city": "Kilbourne",
    "address": "397 Tiffany Place, Sidman, New Mexico, 3774",
    "enabled": true
  },
  {
    "name": "Nora Morse",
    "phone": "+1 (841) 589-2726",
    "city": "Mammoth",
    "address": "398 Devon Avenue, Davenport, Virginia, 7152",
    "enabled": false
  },
  {
    "name": "Acevedo Beach",
    "phone": "+1 (966) 415-2902",
    "city": "Roeville",
    "address": "176 Bergen Place, Noblestown, Kentucky, 4859",
    "enabled": true
  },
  {
    "name": "Charity Hayden",
    "phone": "+1 (883) 590-3093",
    "city": "Elwood",
    "address": "279 Ocean Parkway, Coleville, Massachusetts, 4976",
    "enabled": true
  },
  {
    "name": "Duke Cunningham",
    "phone": "+1 (851) 468-2154",
    "city": "Grantville",
    "address": "365 Perry Terrace, Marysville, Iowa, 2008",
    "enabled": true
  },
  {
    "name": "Morrison Todd",
    "phone": "+1 (935) 576-2208",
    "city": "Woodburn",
    "address": "534 Bedell Lane, Aurora, Virgin Islands, 9109",
    "enabled": true
  },
  {
    "name": "Frost Mathews",
    "phone": "+1 (819) 560-3311",
    "city": "Santel",
    "address": "707 Dooley Street, Klondike, Texas, 9142",
    "enabled": false
  },
  {
    "name": "Carroll Humphrey",
    "phone": "+1 (892) 496-3917",
    "city": "Gouglersville",
    "address": "649 Dakota Place, Williston, Wyoming, 5734",
    "enabled": true
  },
  {
    "name": "Kline Dodson",
    "phone": "+1 (866) 523-3625",
    "city": "Mahtowa",
    "address": "608 Quentin Road, Accoville, North Dakota, 3477",
    "enabled": true
  },
  {
    "name": "Calderon Cox",
    "phone": "+1 (914) 426-2845",
    "city": "Savannah",
    "address": "547 Anthony Street, Dante, Minnesota, 5313",
    "enabled": true
  },
  {
    "name": "Bradshaw Cooper",
    "phone": "+1 (842) 524-2142",
    "city": "Coaldale",
    "address": "560 Dunne Court, Downsville, Connecticut, 203",
    "enabled": true
  },
  {
    "name": "Lilly Nixon",
    "phone": "+1 (970) 543-2936",
    "city": "Hanover",
    "address": "832 Hutchinson Court, Rose, Oklahoma, 6227",
    "enabled": false
  },
  {
    "name": "Kelli Sargent",
    "phone": "+1 (919) 424-2057",
    "city": "Caron",
    "address": "425 Batchelder Street, Shasta, District Of Columbia, 3362",
    "enabled": true
  },
  {
    "name": "Aida Gregory",
    "phone": "+1 (989) 477-2790",
    "city": "Tetherow",
    "address": "985 Conselyea Street, Hannasville, Kansas, 6259",
    "enabled": false
  },
  {
    "name": "Wiggins Charles",
    "phone": "+1 (837) 442-2542",
    "city": "Stockwell",
    "address": "248 Vandam Street, Barstow, Vermont, 4409",
    "enabled": true
  },
  {
    "name": "Vaughn Anthony",
    "phone": "+1 (833) 494-2200",
    "city": "Urie",
    "address": "343 Rutland Road, Stagecoach, Maine, 6552",
    "enabled": true
  },
  {
    "name": "Charlotte Goff",
    "phone": "+1 (863) 508-2186",
    "city": "Cumberland",
    "address": "484 Garden Street, Inkerman, Oregon, 569",
    "enabled": true
  },
  {
    "name": "Parsons Erickson",
    "phone": "+1 (999) 510-2151",
    "city": "Ronco",
    "address": "943 Hunts Lane, Lumberton, Georgia, 6439",
    "enabled": true
  },
  {
    "name": "Bryant Sherman",
    "phone": "+1 (966) 597-2934",
    "city": "Bascom",
    "address": "436 Montague Terrace, Blue, Alaska, 2037",
    "enabled": false
  },
  {
    "name": "Marie Acevedo",
    "phone": "+1 (874) 512-3638",
    "city": "Bowie",
    "address": "259 Ash Street, Frank, New Jersey, 8488",
    "enabled": false
  },
  {
    "name": "Mercado Weeks",
    "phone": "+1 (830) 565-3960",
    "city": "Hailesboro",
    "address": "870 Crown Street, Loyalhanna, Rhode Island, 8444",
    "enabled": false
  },
  {
    "name": "Barron Cote",
    "phone": "+1 (803) 529-2135",
    "city": "Outlook",
    "address": "502 Willoughby Street, Richmond, Federated States Of Micronesia, 4364",
    "enabled": true
  },
  {
    "name": "Eunice Morgan",
    "phone": "+1 (994) 411-3265",
    "city": "Dawn",
    "address": "750 Farragut Road, Crayne, Alabama, 5879",
    "enabled": true
  },
  {
    "name": "Dona Farley",
    "phone": "+1 (867) 474-3949",
    "city": "Shindler",
    "address": "453 Foster Avenue, Sanborn, Puerto Rico, 7637",
    "enabled": false
  },
  {
    "name": "Ochoa Boone",
    "phone": "+1 (917) 463-3952",
    "city": "Adelino",
    "address": "839 Garden Place, Chesterfield, Michigan, 265",
    "enabled": true
  },
  {
    "name": "Consuelo Mccullough",
    "phone": "+1 (841) 410-3107",
    "city": "Baden",
    "address": "644 Beadel Street, Hilltop, American Samoa, 6099",
    "enabled": false
  },
  {
    "name": "Bolton Herman",
    "phone": "+1 (850) 570-3767",
    "city": "Kansas",
    "address": "296 Glenmore Avenue, Eagletown, Illinois, 3233",
    "enabled": true
  },
  {
    "name": "Short Sykes",
    "phone": "+1 (843) 467-2749",
    "city": "Fingerville",
    "address": "728 Nova Court, Fruitdale, Colorado, 5965",
    "enabled": false
  },
  {
    "name": "Griffin Pitts",
    "phone": "+1 (969) 573-2833",
    "city": "Wheaton",
    "address": "877 Gem Street, Idledale, Northern Mariana Islands, 2812",
    "enabled": true
  },
  {
    "name": "Washington Walls",
    "phone": "+1 (939) 459-3395",
    "city": "Camas",
    "address": "304 Durland Place, Malott, Montana, 1845",
    "enabled": true
  },
  {
    "name": "Jeanette Brooks",
    "phone": "+1 (865) 549-3392",
    "city": "Longoria",
    "address": "461 Driggs Avenue, Wauhillau, Utah, 5462",
    "enabled": true
  },
  {
    "name": "Robles Frank",
    "phone": "+1 (923) 540-2049",
    "city": "Cherokee",
    "address": "152 Story Court, Kapowsin, Guam, 7139",
    "enabled": true
  },
  {
    "name": "Lillian Langley",
    "phone": "+1 (896) 597-3808",
    "city": "Glasgow",
    "address": "388 Stuart Street, Neahkahnie, Tennessee, 7233",
    "enabled": true
  },
  {
    "name": "Kristen Bender",
    "phone": "+1 (958) 479-2408",
    "city": "Alleghenyville",
    "address": "261 Scholes Street, Naomi, Nevada, 1300",
    "enabled": true
  },
  {
    "name": "Wong Salas",
    "phone": "+1 (910) 445-3954",
    "city": "Hollins",
    "address": "572 Seaview Avenue, Rosine, Indiana, 2471",
    "enabled": true
  },
  {
    "name": "Tran Burgess",
    "phone": "+1 (971) 521-3355",
    "city": "Loveland",
    "address": "742 Ellery Street, Belleview, New Hampshire, 2645",
    "enabled": false
  },
  {
    "name": "Olivia Mcpherson",
    "phone": "+1 (807) 558-3575",
    "city": "Vienna",
    "address": "988 Crawford Avenue, Matthews, West Virginia, 8004",
    "enabled": false
  },
  {
    "name": "Kellie Daniel",
    "phone": "+1 (816) 561-2048",
    "city": "Boling",
    "address": "545 Wolcott Street, Bradenville, Wisconsin, 2622",
    "enabled": true
  },
  {
    "name": "Lucile Leon",
    "phone": "+1 (963) 528-2497",
    "city": "Magnolia",
    "address": "702 Dekalb Avenue, Heil, New York, 3627",
    "enabled": false
  },
  {
    "name": "Augusta Moss",
    "phone": "+1 (839) 453-2741",
    "city": "Allendale",
    "address": "146 Java Street, Weedville, California, 4419",
    "enabled": false
  },
  {
    "name": "Swanson Dunlap",
    "phone": "+1 (922) 478-3017",
    "city": "Alfarata",
    "address": "368 Radde Place, Farmington, Palau, 2723",
    "enabled": true
  },
  {
    "name": "French George",
    "phone": "+1 (890) 402-3963",
    "city": "Datil",
    "address": "670 Ovington Court, Comptche, Idaho, 6944",
    "enabled": true
  },
  {
    "name": "Hubbard Franks",
    "phone": "+1 (881) 581-3025",
    "city": "Weeksville",
    "address": "322 Adelphi Street, Ebro, Florida, 4272",
    "enabled": false
  },
  {
    "name": "Vilma Browning",
    "phone": "+1 (970) 422-3026",
    "city": "Golconda",
    "address": "198 Laurel Avenue, Groton, Mississippi, 6014",
    "enabled": false
  },
  {
    "name": "House Patrick",
    "phone": "+1 (875) 545-2955",
    "city": "Harmon",
    "address": "864 Harman Street, Silkworth, North Carolina, 3361",
    "enabled": true
  },
  {
    "name": "Webster Molina",
    "phone": "+1 (825) 488-3032",
    "city": "Bison",
    "address": "118 Love Lane, Lithium, Maryland, 3519",
    "enabled": false
  },
  {
    "name": "Owen Hale",
    "phone": "+1 (965) 430-2894",
    "city": "Chemung",
    "address": "474 Box Street, Leroy, Washington, 6081",
    "enabled": true
  },
  {
    "name": "Merle Fry",
    "phone": "+1 (901) 467-2597",
    "city": "Mulberry",
    "address": "420 Belvidere Street, Iola, Arizona, 8666",
    "enabled": true
  },
  {
    "name": "Rochelle Woodard",
    "phone": "+1 (949) 492-2441",
    "city": "Bynum",
    "address": "399 Stratford Road, Ypsilanti, Hawaii, 2424",
    "enabled": true
  },
  {
    "name": "Garrison Baldwin",
    "phone": "+1 (961) 573-3097",
    "city": "Leland",
    "address": "326 Carlton Avenue, Beason, Ohio, 4264",
    "enabled": false
  },
  {
    "name": "Claudette Romero",
    "phone": "+1 (812) 435-3928",
    "city": "Mathews",
    "address": "840 Huntington Street, Joes, South Carolina, 1555",
    "enabled": false
  },
  {
    "name": "Sue Ferguson",
    "phone": "+1 (949) 535-2735",
    "city": "Corinne",
    "address": "442 Kent Street, Staples, South Dakota, 1815",
    "enabled": false
  },
  {
    "name": "Pollard Crosby",
    "phone": "+1 (828) 553-2220",
    "city": "Southview",
    "address": "845 Halsey Street, Innsbrook, Delaware, 5687",
    "enabled": false
  },
  {
    "name": "Kelley Clarke",
    "phone": "+1 (864) 531-3620",
    "city": "Walker",
    "address": "145 Stillwell Place, Cliffside, Nebraska, 874",
    "enabled": true
  },
  {
    "name": "Ayala Perez",
    "phone": "+1 (822) 563-3929",
    "city": "Boomer",
    "address": "214 Baughman Place, Sheatown, Pennsylvania, 4897",
    "enabled": false
  },
  {
    "name": "Hampton Massey",
    "phone": "+1 (912) 527-2043",
    "city": "Crawfordsville",
    "address": "903 Ivan Court, Woodlake, Louisiana, 641",
    "enabled": false
  },
  {
    "name": "Gwen English",
    "phone": "+1 (804) 401-3590",
    "city": "Floris",
    "address": "365 Kingston Avenue, Healy, Arkansas, 9176",
    "enabled": true
  },
  {
    "name": "Sheri Holloway",
    "phone": "+1 (846) 436-2304",
    "city": "Waukeenah",
    "address": "943 Greenpoint Avenue, Roosevelt, Marshall Islands, 1438",
    "enabled": false
  },
  {
    "name": "Kirsten Avery",
    "phone": "+1 (850) 412-2880",
    "city": "Skyland",
    "address": "353 Bowery Street, Whitehaven, New Mexico, 905",
    "enabled": true
  },
  {
    "name": "Lorraine Galloway",
    "phone": "+1 (935) 582-3784",
    "city": "Stonybrook",
    "address": "994 Neptune Court, Whipholt, Virginia, 9920",
    "enabled": false
  },
  {
    "name": "Bray Bush",
    "phone": "+1 (993) 582-2522",
    "city": "Retsof",
    "address": "487 Remsen Street, Ticonderoga, Kentucky, 1474",
    "enabled": false
  },
  {
    "name": "Trisha Barr",
    "phone": "+1 (984) 505-2066",
    "city": "Barrelville",
    "address": "401 Agate Court, Hebron, Massachusetts, 3748",
    "enabled": true
  },
  {
    "name": "Terri Carey",
    "phone": "+1 (819) 483-2308",
    "city": "Lopezo",
    "address": "951 Bridge Street, Strykersville, Iowa, 8370",
    "enabled": true
  },
  {
    "name": "Fowler Snider",
    "phone": "+1 (878) 454-3338",
    "city": "Troy",
    "address": "135 Lawton Street, Gallina, Virgin Islands, 884",
    "enabled": false
  },
  {
    "name": "Vicki Delacruz",
    "phone": "+1 (920) 552-2389",
    "city": "Masthope",
    "address": "213 Varick Street, Logan, Texas, 3069",
    "enabled": false
  },
  {
    "name": "Patty Moore",
    "phone": "+1 (933) 460-2601",
    "city": "Rodman",
    "address": "962 Clark Street, Keller, Wyoming, 2260",
    "enabled": false
  },
  {
    "name": "Ronda Burton",
    "phone": "+1 (848) 584-2464",
    "city": "Rote",
    "address": "544 Turnbull Avenue, Hoagland, North Dakota, 1860",
    "enabled": false
  },
  {
    "name": "Velazquez Swanson",
    "phone": "+1 (956) 597-3133",
    "city": "Nadine",
    "address": "470 Lake Street, Oretta, Minnesota, 6606",
    "enabled": true
  },
  {
    "name": "Carole Stevenson",
    "phone": "+1 (850) 409-2853",
    "city": "Hollymead",
    "address": "603 Hunterfly Place, Dragoon, Connecticut, 6590",
    "enabled": true
  },
  {
    "name": "Tonia Vance",
    "phone": "+1 (915) 589-3696",
    "city": "Denio",
    "address": "234 Canal Avenue, Graball, Oklahoma, 8773",
    "enabled": true
  },
  {
    "name": "Buckner Pearson",
    "phone": "+1 (833) 437-2351",
    "city": "Sims",
    "address": "354 Hubbard Place, Nicholson, District Of Columbia, 5199",
    "enabled": true
  },
  {
    "name": "Florine Hanson",
    "phone": "+1 (955) 414-2460",
    "city": "Cartwright",
    "address": "822 Grand Avenue, Esmont, Kansas, 4392",
    "enabled": true
  },
  {
    "name": "Tyson Graham",
    "phone": "+1 (868) 587-2623",
    "city": "Hillsboro",
    "address": "615 Junius Street, Worcester, Vermont, 1594",
    "enabled": false
  },
  {
    "name": "Manning Patel",
    "phone": "+1 (876) 528-3685",
    "city": "Edinburg",
    "address": "937 Erasmus Street, Harleigh, Maine, 7019",
    "enabled": false
  },
  {
    "name": "Mattie Conner",
    "phone": "+1 (868) 537-2316",
    "city": "Cetronia",
    "address": "352 Brevoort Place, Camptown, Oregon, 507",
    "enabled": false
  },
  {
    "name": "Pam Hopkins",
    "phone": "+1 (878) 495-3766",
    "city": "Hampstead",
    "address": "225 Bleecker Street, Williamson, Georgia, 2761",
    "enabled": true
  },
  {
    "name": "Kendra Mcintosh",
    "phone": "+1 (880) 526-2465",
    "city": "Fulford",
    "address": "337 Henry Street, Deercroft, Alaska, 1801",
    "enabled": false
  },
  {
    "name": "Shelby Cummings",
    "phone": "+1 (875) 434-2381",
    "city": "Beechmont",
    "address": "218 Norwood Avenue, Orason, New Jersey, 2893",
    "enabled": true
  },
  {
    "name": "Trudy Middleton",
    "phone": "+1 (998) 509-2942",
    "city": "Bluffview",
    "address": "135 Lincoln Terrace, Vernon, Rhode Island, 9315",
    "enabled": true
  },
  {
    "name": "Elliott Cruz",
    "phone": "+1 (804) 554-3440",
    "city": "Bedias",
    "address": "251 Girard Street, Northridge, Federated States Of Micronesia, 8560",
    "enabled": false
  },
  {
    "name": "David Buckner",
    "phone": "+1 (825) 486-3092",
    "city": "Collins",
    "address": "645 Kansas Place, Brutus, Alabama, 918",
    "enabled": true
  },
  {
    "name": "Stevenson Monroe",
    "phone": "+1 (987) 505-3695",
    "city": "Macdona",
    "address": "987 Madison Street, Morningside, Puerto Rico, 3213",
    "enabled": false
  },
  {
    "name": "Tameka Gay",
    "phone": "+1 (866) 498-2587",
    "city": "Montura",
    "address": "867 Hendrickson Street, Thynedale, Michigan, 5152",
    "enabled": true
  },
  {
    "name": "Campos Castro",
    "phone": "+1 (875) 500-3901",
    "city": "Elliott",
    "address": "347 Sandford Street, Hayes, American Samoa, 344",
    "enabled": false
  },
  {
    "name": "Nolan Best",
    "phone": "+1 (975) 550-2118",
    "city": "Linwood",
    "address": "347 Regent Place, Fairlee, Illinois, 4642",
    "enabled": true
  },
  {
    "name": "Finley Hurst",
    "phone": "+1 (987) 587-3042",
    "city": "Wyoming",
    "address": "139 Monitor Street, Grenelefe, Colorado, 5220",
    "enabled": false
  },
  {
    "name": "Barnes Gibson",
    "phone": "+1 (876) 574-3214",
    "city": "Grazierville",
    "address": "169 Irving Avenue, Lutsen, Northern Mariana Islands, 9645",
    "enabled": true
  },
  {
    "name": "English Daugherty",
    "phone": "+1 (871) 497-3540",
    "city": "Jessie",
    "address": "904 Furman Street, Roberts, Montana, 1034",
    "enabled": false
  },
  {
    "name": "Roxanne Rodriquez",
    "phone": "+1 (963) 446-2762",
    "city": "Norvelt",
    "address": "748 Adler Place, Axis, Utah, 3878",
    "enabled": false
  },
  {
    "name": "Ingram Chandler",
    "phone": "+1 (921) 513-2895",
    "city": "Lund",
    "address": "301 Waldane Court, Guilford, Guam, 6331",
    "enabled": true
  },
  {
    "name": "Estella Reynolds",
    "phone": "+1 (975) 578-3257",
    "city": "Brandermill",
    "address": "100 Vermont Street, National, Tennessee, 7828",
    "enabled": false
  },
  {
    "name": "Jolene Baker",
    "phone": "+1 (916) 507-2642",
    "city": "Cashtown",
    "address": "906 Canton Court, Dupuyer, Nevada, 1323",
    "enabled": true
  },
  {
    "name": "Shawna Roy",
    "phone": "+1 (820) 432-2151",
    "city": "Valle",
    "address": "967 Brigham Street, Farmers, Indiana, 181",
    "enabled": false
  },
  {
    "name": "Deann Lambert",
    "phone": "+1 (817) 532-3577",
    "city": "Hasty",
    "address": "317 Hausman Street, Norris, New Hampshire, 8215",
    "enabled": true
  },
  {
    "name": "Delacruz Grant",
    "phone": "+1 (976) 477-2265",
    "city": "Stouchsburg",
    "address": "667 Gerry Street, Avoca, West Virginia, 3545",
    "enabled": false
  },
  {
    "name": "Nannie Jacobs",
    "phone": "+1 (869) 534-3705",
    "city": "Coventry",
    "address": "317 Landis Court, Juntura, Wisconsin, 2480",
    "enabled": true
  },
  {
    "name": "Stacey House",
    "phone": "+1 (929) 554-2505",
    "city": "Elliston",
    "address": "515 Maple Street, Matheny, New York, 7458",
    "enabled": true
  },
  {
    "name": "Beth Rice",
    "phone": "+1 (945) 513-3367",
    "city": "Nash",
    "address": "930 Dunham Place, Sisquoc, California, 7198",
    "enabled": false
  },
  {
    "name": "Garrett Hutchinson",
    "phone": "+1 (953) 582-2561",
    "city": "Moscow",
    "address": "580 Oxford Walk, Twilight, Palau, 5285",
    "enabled": false
  },
  {
    "name": "Holden Boyer",
    "phone": "+1 (855) 477-2462",
    "city": "Cawood",
    "address": "732 Elizabeth Place, Galesville, Idaho, 7222",
    "enabled": true
  },
  {
    "name": "Valdez Andrews",
    "phone": "+1 (868) 421-3862",
    "city": "Wilsonia",
    "address": "364 Flatlands Avenue, Carrsville, Florida, 9912",
    "enabled": false
  },
  {
    "name": "Walsh Velasquez",
    "phone": "+1 (831) 412-3770",
    "city": "Homestead",
    "address": "566 Trucklemans Lane, Bordelonville, Mississippi, 3262",
    "enabled": false
  },
  {
    "name": "Laverne Rocha",
    "phone": "+1 (957) 486-2902",
    "city": "Cade",
    "address": "146 Murdock Court, Kieler, North Carolina, 1562",
    "enabled": false
  },
  {
    "name": "Cecilia Peterson",
    "phone": "+1 (812) 424-3394",
    "city": "Hartsville/Hartley",
    "address": "582 Sedgwick Street, Southmont, Maryland, 994",
    "enabled": true
  },
  {
    "name": "Kari Mcneil",
    "phone": "+1 (978) 559-2558",
    "city": "Rivera",
    "address": "294 Fanchon Place, Graniteville, Washington, 5269",
    "enabled": false
  },
  {
    "name": "Mullins Noel",
    "phone": "+1 (985) 500-2924",
    "city": "Dodge",
    "address": "155 Clarendon Road, Hemlock, Arizona, 8106",
    "enabled": true
  },
  {
    "name": "Gabriela Ruiz",
    "phone": "+1 (971) 590-3297",
    "city": "Bartley",
    "address": "647 Tech Place, Taycheedah, Hawaii, 2812",
    "enabled": true
  },
  {
    "name": "Magdalena Savage",
    "phone": "+1 (879) 581-3277",
    "city": "Siglerville",
    "address": "106 Bergen Street, Curtice, Ohio, 903",
    "enabled": true
  },
  {
    "name": "Dianne Mitchell",
    "phone": "+1 (860) 505-2244",
    "city": "Kohatk",
    "address": "684 Windsor Place, Caspar, South Carolina, 8032",
    "enabled": true
  },
  {
    "name": "Alba Barker",
    "phone": "+1 (867) 425-2028",
    "city": "Deseret",
    "address": "328 Middleton Street, Elfrida, South Dakota, 3315",
    "enabled": false
  },
  {
    "name": "Jacquelyn Bonner",
    "phone": "+1 (838) 406-2310",
    "city": "Diaperville",
    "address": "403 Lamont Court, Reinerton, Delaware, 5029",
    "enabled": true
  },
  {
    "name": "Mitchell Cleveland",
    "phone": "+1 (988) 483-3524",
    "city": "Kenwood",
    "address": "211 Roder Avenue, Lowgap, Nebraska, 9723",
    "enabled": false
  },
  {
    "name": "Woods Hogan",
    "phone": "+1 (903) 400-2769",
    "city": "Waiohinu",
    "address": "101 Gilmore Court, Marshall, Pennsylvania, 9979",
    "enabled": false
  },
  {
    "name": "Ayers Chapman",
    "phone": "+1 (849) 540-3430",
    "city": "Thornport",
    "address": "783 Vista Place, Clinton, Louisiana, 844",
    "enabled": true
  },
  {
    "name": "Mckee Hunter",
    "phone": "+1 (909) 534-2162",
    "city": "Grandview",
    "address": "483 Amber Street, Rowe, Arkansas, 5518",
    "enabled": false
  },
  {
    "name": "Bessie Carson",
    "phone": "+1 (966) 426-3348",
    "city": "Springville",
    "address": "656 Fleet Place, Goochland, Marshall Islands, 1998",
    "enabled": true
  },
  {
    "name": "Maria Ramos",
    "phone": "+1 (951) 507-2154",
    "city": "Vincent",
    "address": "744 Rockaway Parkway, Temperanceville, New Mexico, 6822",
    "enabled": false
  },
  {
    "name": "Katy Casey",
    "phone": "+1 (866) 578-2085",
    "city": "Enetai",
    "address": "586 Kensington Walk, Lavalette, Virginia, 4496",
    "enabled": false
  },
  {
    "name": "Francisca Bruce",
    "phone": "+1 (883) 560-2482",
    "city": "Sunbury",
    "address": "654 Schenck Avenue, Wattsville, Kentucky, 6042",
    "enabled": false
  },
  {
    "name": "Effie Mclean",
    "phone": "+1 (973) 400-2094",
    "city": "Wescosville",
    "address": "327 Glendale Court, Westboro, Massachusetts, 1242",
    "enabled": false
  },
  {
    "name": "Blackburn Callahan",
    "phone": "+1 (913) 530-3357",
    "city": "Canoochee",
    "address": "783 Bank Street, Hatteras, Iowa, 2318",
    "enabled": true
  },
  {
    "name": "Watson Hickman",
    "phone": "+1 (844) 583-2818",
    "city": "Freetown",
    "address": "709 Newport Street, Rivereno, Virgin Islands, 7458",
    "enabled": true
  },
  {
    "name": "Muriel Wilkins",
    "phone": "+1 (838) 548-3366",
    "city": "Utting",
    "address": "158 Coyle Street, Dyckesville, Texas, 2313",
    "enabled": false
  },
  {
    "name": "Hendrix Mcknight",
    "phone": "+1 (835) 450-2625",
    "city": "Ezel",
    "address": "657 Putnam Avenue, Blackgum, Wyoming, 7911",
    "enabled": false
  },
  {
    "name": "Celeste Ware",
    "phone": "+1 (943) 400-3595",
    "city": "Chesapeake",
    "address": "228 Beverly Road, Rockhill, North Dakota, 6734",
    "enabled": false
  },
  {
    "name": "Snyder Henson",
    "phone": "+1 (909) 489-3770",
    "city": "Berlin",
    "address": "938 Delevan Street, Robbins, Minnesota, 3319",
    "enabled": true
  },
  {
    "name": "Randolph Sutton",
    "phone": "+1 (823) 513-2763",
    "city": "Glenville",
    "address": "528 Seton Place, Dana, Connecticut, 3156",
    "enabled": false
  },
  {
    "name": "Morales Dunn",
    "phone": "+1 (807) 600-3620",
    "city": "Tuttle",
    "address": "963 Fleet Walk, Cowiche, Oklahoma, 5469",
    "enabled": false
  },
  {
    "name": "Rowland Howe",
    "phone": "+1 (811) 581-2955",
    "city": "Wakarusa",
    "address": "470 Wyona Street, Lupton, District Of Columbia, 6671",
    "enabled": true
  },
  {
    "name": "Burt Hart",
    "phone": "+1 (887) 563-2271",
    "city": "Cleary",
    "address": "700 Blake Avenue, Cornfields, Kansas, 8324",
    "enabled": true
  },
  {
    "name": "Araceli King",
    "phone": "+1 (844) 581-2926",
    "city": "Yorklyn",
    "address": "765 King Street, Canby, Vermont, 2267",
    "enabled": false
  },
  {
    "name": "Noel Hess",
    "phone": "+1 (891) 574-3584",
    "city": "Brownsville",
    "address": "728 Ridgewood Place, Slovan, Maine, 3695",
    "enabled": false
  },
  {
    "name": "Drake Faulkner",
    "phone": "+1 (865) 407-2576",
    "city": "Salvo",
    "address": "434 Albemarle Road, Richville, Oregon, 8016",
    "enabled": true
  },
  {
    "name": "Rosie Benjamin",
    "phone": "+1 (889) 461-3612",
    "city": "Winfred",
    "address": "108 Willow Street, Kula, Georgia, 9148",
    "enabled": false
  },
  {
    "name": "Frances Wilson",
    "phone": "+1 (819) 530-3845",
    "city": "Brethren",
    "address": "860 Poplar Street, Kenmar, Alaska, 989",
    "enabled": true
  },
  {
    "name": "Leola Odonnell",
    "phone": "+1 (998) 424-3324",
    "city": "Sylvanite",
    "address": "662 Debevoise Street, Kraemer, New Jersey, 9164",
    "enabled": true
  },
  {
    "name": "Kennedy Spears",
    "phone": "+1 (922) 405-3109",
    "city": "Blandburg",
    "address": "322 Green Street, Welch, Rhode Island, 1579",
    "enabled": true
  },
  {
    "name": "Page Carpenter",
    "phone": "+1 (865) 522-3957",
    "city": "Carlos",
    "address": "925 Clay Street, Bentley, Federated States Of Micronesia, 2104",
    "enabled": true
  },
  {
    "name": "Montoya Mccormick",
    "phone": "+1 (970) 550-2426",
    "city": "Succasunna",
    "address": "508 Jerome Street, Edenburg, Alabama, 1199",
    "enabled": true
  },
  {
    "name": "Hays Gamble",
    "phone": "+1 (913) 442-2113",
    "city": "Grill",
    "address": "250 Poly Place, Chestnut, Puerto Rico, 1082",
    "enabled": false
  },
  {
    "name": "Juana Martin",
    "phone": "+1 (966) 474-3414",
    "city": "Kent",
    "address": "401 Townsend Street, Wadsworth, Michigan, 6853",
    "enabled": true
  },
  {
    "name": "Rhodes Wise",
    "phone": "+1 (998) 430-2936",
    "city": "Vicksburg",
    "address": "343 Luquer Street, Grayhawk, American Samoa, 6500",
    "enabled": false
  },
  {
    "name": "Petty Barrett",
    "phone": "+1 (974) 580-2420",
    "city": "Glenshaw",
    "address": "389 Railroad Avenue, Convent, Illinois, 5670",
    "enabled": true
  },
  {
    "name": "Gretchen Pace",
    "phone": "+1 (921) 583-2734",
    "city": "Boykin",
    "address": "550 Pulaski Street, Unionville, Colorado, 1409",
    "enabled": true
  },
  {
    "name": "Travis Evans",
    "phone": "+1 (908) 415-3933",
    "city": "Courtland",
    "address": "712 Bay Parkway, Lemoyne, Northern Mariana Islands, 2540",
    "enabled": false
  },
  {
    "name": "Peck Joseph",
    "phone": "+1 (956) 444-2167",
    "city": "Kylertown",
    "address": "916 Greene Avenue, Genoa, Montana, 7171",
    "enabled": false
  },
  {
    "name": "Shepherd Vinson",
    "phone": "+1 (989) 530-2907",
    "city": "Churchill",
    "address": "468 Alabama Avenue, Cornucopia, Utah, 7944",
    "enabled": false
  },
  {
    "name": "Wise Ward",
    "phone": "+1 (894) 498-3030",
    "city": "Winston",
    "address": "922 Rockaway Avenue, Geyserville, Guam, 1753",
    "enabled": false
  },
  {
    "name": "Booth Melton",
    "phone": "+1 (910) 544-3123",
    "city": "Tivoli",
    "address": "596 Aster Court, Cloverdale, Tennessee, 8530",
    "enabled": false
  },
  {
    "name": "Atkinson Harper",
    "phone": "+1 (985) 548-3156",
    "city": "Levant",
    "address": "419 Rutherford Place, Zeba, Nevada, 9061",
    "enabled": true
  },
  {
    "name": "Sloan Mcintyre",
    "phone": "+1 (805) 450-3223",
    "city": "Cassel",
    "address": "266 Hanover Place, Gordon, Indiana, 2827",
    "enabled": true
  },
  {
    "name": "Norma Eaton",
    "phone": "+1 (819) 441-2687",
    "city": "Mappsville",
    "address": "753 Seba Avenue, Grimsley, New Hampshire, 6363",
    "enabled": true
  },
  {
    "name": "Abbott Talley",
    "phone": "+1 (971) 513-2705",
    "city": "Catherine",
    "address": "523 Rock Street, Starks, West Virginia, 2614",
    "enabled": true
  },
  {
    "name": "Sabrina Schroeder",
    "phone": "+1 (846) 551-2622",
    "city": "Bawcomville",
    "address": "400 McKinley Avenue, Robinson, Wisconsin, 9625",
    "enabled": true
  },
  {
    "name": "Mayer Fleming",
    "phone": "+1 (994) 565-3571",
    "city": "Winchester",
    "address": "183 Howard Avenue, Joppa, New York, 2914",
    "enabled": false
  },
  {
    "name": "Vera Delaney",
    "phone": "+1 (857) 596-2943",
    "city": "Nord",
    "address": "153 Grand Street, Caroleen, California, 7851",
    "enabled": true
  },
  {
    "name": "Figueroa Parks",
    "phone": "+1 (918) 478-2797",
    "city": "Ribera",
    "address": "841 Plaza Street, Hoehne, Palau, 691",
    "enabled": true
  },
  {
    "name": "Lois Dotson",
    "phone": "+1 (842) 563-3603",
    "city": "Fairacres",
    "address": "308 Wilson Street, Maplewood, Idaho, 288",
    "enabled": true
  },
  {
    "name": "Jordan Rivera",
    "phone": "+1 (838) 583-3180",
    "city": "Roy",
    "address": "897 Will Place, Welda, Florida, 6703",
    "enabled": false
  },
  {
    "name": "Mindy Manning",
    "phone": "+1 (846) 511-2588",
    "city": "Benson",
    "address": "147 High Street, Makena, Mississippi, 5886",
    "enabled": true
  },
  {
    "name": "Crane Walter",
    "phone": "+1 (956) 478-2059",
    "city": "Stewartville",
    "address": "266 Bainbridge Street, Duryea, North Carolina, 1769",
    "enabled": true
  },
  {
    "name": "Robertson Powell",
    "phone": "+1 (947) 456-3818",
    "city": "Efland",
    "address": "693 Channel Avenue, Moquino, Maryland, 4323",
    "enabled": false
  },
  {
    "name": "Welch Moon",
    "phone": "+1 (851) 454-2696",
    "city": "Rockbridge",
    "address": "982 Ridge Court, Cataract, Washington, 7448",
    "enabled": false
  },
  {
    "name": "Christa Mooney",
    "phone": "+1 (886) 561-3905",
    "city": "Cochranville",
    "address": "962 Seagate Avenue, Florence, Arizona, 7768",
    "enabled": false
  },
  {
    "name": "Sawyer Nelson",
    "phone": "+1 (821) 592-2833",
    "city": "Bluetown",
    "address": "885 Crystal Street, Craig, Hawaii, 5039",
    "enabled": true
  },
  {
    "name": "Beryl Trevino",
    "phone": "+1 (904) 471-2580",
    "city": "Helen",
    "address": "877 Canda Avenue, Belgreen, Ohio, 9121",
    "enabled": false
  },
  {
    "name": "Torres Norris",
    "phone": "+1 (873) 507-3659",
    "city": "Shawmut",
    "address": "160 Strauss Street, Tyro, South Carolina, 7549",
    "enabled": true
  },
  {
    "name": "Kris Mercado",
    "phone": "+1 (821) 570-3638",
    "city": "Gwynn",
    "address": "648 Howard Place, Conway, South Dakota, 8720",
    "enabled": false
  },
  {
    "name": "Cline Workman",
    "phone": "+1 (960) 420-3133",
    "city": "Riverton",
    "address": "205 Tompkins Avenue, Shaft, Delaware, 6785",
    "enabled": true
  },
  {
    "name": "Tabatha Hunt",
    "phone": "+1 (993) 401-2438",
    "city": "Lewis",
    "address": "827 Schenck Street, Snowville, Nebraska, 5874",
    "enabled": false
  },
  {
    "name": "Best Sweet",
    "phone": "+1 (951) 408-3402",
    "city": "Draper",
    "address": "685 Chestnut Avenue, Navarre, Pennsylvania, 9409",
    "enabled": false
  },
  {
    "name": "Mullen Parker",
    "phone": "+1 (812) 566-2866",
    "city": "Vale",
    "address": "489 Lancaster Avenue, Fredericktown, Louisiana, 8674",
    "enabled": false
  },
  {
    "name": "Lindsey Kim",
    "phone": "+1 (864) 466-2326",
    "city": "Rew",
    "address": "296 Church Avenue, Dorneyville, Arkansas, 5905",
    "enabled": false
  },
  {
    "name": "Elnora Mathis",
    "phone": "+1 (984) 544-3894",
    "city": "Coinjock",
    "address": "885 Bragg Street, Noxen, Marshall Islands, 5295",
    "enabled": false
  },
  {
    "name": "Hickman Livingston",
    "phone": "+1 (847) 532-3253",
    "city": "Chumuckla",
    "address": "876 Front Street, Winesburg, New Mexico, 3131",
    "enabled": true
  },
  {
    "name": "Marian Guy",
    "phone": "+1 (947) 421-2989",
    "city": "Goldfield",
    "address": "451 Hubbard Street, Camino, Virginia, 3761",
    "enabled": false
  },
  {
    "name": "Jana Holcomb",
    "phone": "+1 (941) 499-3583",
    "city": "Chelsea",
    "address": "189 Seaview Court, Greenwich, Kentucky, 6571",
    "enabled": false
  },
  {
    "name": "Liza Nicholson",
    "phone": "+1 (882) 489-2025",
    "city": "Marne",
    "address": "932 McDonald Avenue, Rivers, Massachusetts, 8548",
    "enabled": true
  },
  {
    "name": "Marisol Hebert",
    "phone": "+1 (819) 503-3815",
    "city": "Centerville",
    "address": "837 Whitwell Place, Dunlo, Iowa, 1341",
    "enabled": false
  },
  {
    "name": "Glenn Howard",
    "phone": "+1 (880) 558-3433",
    "city": "Lookingglass",
    "address": "976 Division Avenue, Veyo, Virgin Islands, 5709",
    "enabled": false
  },
  {
    "name": "Betsy Hoover",
    "phone": "+1 (839) 497-3707",
    "city": "Saddlebrooke",
    "address": "226 Bulwer Place, Warsaw, Texas, 7329",
    "enabled": true
  },
  {
    "name": "Wall Wooten",
    "phone": "+1 (855) 421-3380",
    "city": "Venice",
    "address": "671 Louisa Street, Villarreal, Wyoming, 163",
    "enabled": true
  },
  {
    "name": "Wilder Pruitt",
    "phone": "+1 (965) 527-2087",
    "city": "Coloma",
    "address": "781 Tompkins Place, Ladera, North Dakota, 9320",
    "enabled": false
  },
  {
    "name": "Carver Mendez",
    "phone": "+1 (857) 589-3724",
    "city": "Bowden",
    "address": "158 Gelston Avenue, Crumpler, Minnesota, 1351",
    "enabled": true
  },
  {
    "name": "Pearl Cotton",
    "phone": "+1 (948) 431-2325",
    "city": "Coral",
    "address": "589 Empire Boulevard, Ruffin, Connecticut, 9288",
    "enabled": false
  },
  {
    "name": "Vincent Oconnor",
    "phone": "+1 (917) 476-3899",
    "city": "Blanford",
    "address": "878 Moore Street, Marbury, Oklahoma, 5524",
    "enabled": true
  },
  {
    "name": "Underwood Sparks",
    "phone": "+1 (914) 580-2485",
    "city": "Bergoo",
    "address": "737 Grafton Street, Garberville, District Of Columbia, 2059",
    "enabled": false
  },
  {
    "name": "Katelyn Ford",
    "phone": "+1 (820) 401-2684",
    "city": "Itmann",
    "address": "819 Highland Avenue, Eggertsville, Kansas, 1911",
    "enabled": false
  },
  {
    "name": "Priscilla Moody",
    "phone": "+1 (904) 472-2370",
    "city": "Mayfair",
    "address": "547 Sumpter Street, Cecilia, Vermont, 5202",
    "enabled": true
  },
  {
    "name": "Guerrero Emerson",
    "phone": "+1 (833) 411-2966",
    "city": "Westmoreland",
    "address": "244 Berriman Street, Gorham, Maine, 5487",
    "enabled": false
  },
  {
    "name": "Emerson James",
    "phone": "+1 (902) 479-2086",
    "city": "Goodville",
    "address": "741 Troy Avenue, Eureka, Oregon, 9692",
    "enabled": true
  },
  {
    "name": "Marlene Kennedy",
    "phone": "+1 (839) 596-2350",
    "city": "Alden",
    "address": "957 Homecrest Court, Saranap, Georgia, 6280",
    "enabled": false
  },
  {
    "name": "Beatriz Nunez",
    "phone": "+1 (952) 484-3234",
    "city": "Wawona",
    "address": "383 Noll Street, Cumminsville, Alaska, 625",
    "enabled": false
  },
  {
    "name": "Sheila Garner",
    "phone": "+1 (816) 461-2571",
    "city": "Madrid",
    "address": "753 Hendrix Street, Clay, New Jersey, 7419",
    "enabled": true
  },
  {
    "name": "Ellison Harrington",
    "phone": "+1 (866) 456-2533",
    "city": "Northchase",
    "address": "667 Knight Court, Nanafalia, Rhode Island, 5697",
    "enabled": true
  },
  {
    "name": "Elena White",
    "phone": "+1 (803) 584-3651",
    "city": "Oceola",
    "address": "379 Pierrepont Street, Dexter, Federated States Of Micronesia, 5043",
    "enabled": false
  },
  {
    "name": "Ferguson Riley",
    "phone": "+1 (927) 447-3582",
    "city": "Fairhaven",
    "address": "886 Celeste Court, Brecon, Alabama, 2096",
    "enabled": false
  },
  {
    "name": "Maxine Montgomery",
    "phone": "+1 (974) 548-2872",
    "city": "Watchtower",
    "address": "215 Diamond Street, Clarktown, Puerto Rico, 671",
    "enabled": true
  },
  {
    "name": "Mathews Hammond",
    "phone": "+1 (860) 414-2666",
    "city": "Tooleville",
    "address": "783 Colonial Road, Harrison, Michigan, 4483",
    "enabled": true
  },
  {
    "name": "Bright Medina",
    "phone": "+1 (911) 552-3117",
    "city": "Catharine",
    "address": "664 Cropsey Avenue, Bethpage, American Samoa, 622",
    "enabled": true
  },
  {
    "name": "Higgins Mejia",
    "phone": "+1 (873) 406-3597",
    "city": "Nelson",
    "address": "209 Bath Avenue, Brogan, Illinois, 9858",
    "enabled": false
  },
  {
    "name": "Aurora Garrett",
    "phone": "+1 (835) 508-2786",
    "city": "Lindisfarne",
    "address": "260 Cameron Court, Monument, Colorado, 5964",
    "enabled": false
  },
  {
    "name": "Amparo Solomon",
    "phone": "+1 (807) 401-3348",
    "city": "Chalfant",
    "address": "511 Nevins Street, Gerber, Northern Mariana Islands, 8541",
    "enabled": true
  },
  {
    "name": "Wells Potter",
    "phone": "+1 (819) 402-3169",
    "city": "Chase",
    "address": "758 Mill Street, Trexlertown, Montana, 145",
    "enabled": false
  },
  {
    "name": "Hood Flores",
    "phone": "+1 (906) 544-3392",
    "city": "Why",
    "address": "949 Douglass Street, Glendale, Utah, 1176",
    "enabled": false
  },
  {
    "name": "Mccormick Jackson",
    "phone": "+1 (957) 457-2655",
    "city": "Foscoe",
    "address": "578 Coleridge Street, Sharon, Guam, 8300",
    "enabled": true
  },
  {
    "name": "Mcfadden Terry",
    "phone": "+1 (864) 461-3505",
    "city": "Fontanelle",
    "address": "735 Tampa Court, Omar, Tennessee, 2209",
    "enabled": false
  },
  {
    "name": "Adele Wynn",
    "phone": "+1 (853) 590-2074",
    "city": "Allison",
    "address": "900 Caton Avenue, Libertytown, Nevada, 6969",
    "enabled": false
  },
  {
    "name": "Lyons Alvarado",
    "phone": "+1 (982) 402-2004",
    "city": "Olney",
    "address": "441 Banker Street, Brambleton, Indiana, 2660",
    "enabled": false
  },
  {
    "name": "Bridget Roberts",
    "phone": "+1 (961) 543-3080",
    "city": "Jardine",
    "address": "370 Elm Avenue, Imperial, New Hampshire, 8999",
    "enabled": true
  },
  {
    "name": "Marquita Wheeler",
    "phone": "+1 (965) 486-2194",
    "city": "Coldiron",
    "address": "797 Harbor Court, Leming, West Virginia, 5235",
    "enabled": false
  },
  {
    "name": "Decker Santana",
    "phone": "+1 (895) 482-3919",
    "city": "Gila",
    "address": "102 Berkeley Place, Dalton, Wisconsin, 7231",
    "enabled": true
  },
  {
    "name": "Erma Mcclure",
    "phone": "+1 (973) 461-2331",
    "city": "Kempton",
    "address": "838 Georgia Avenue, Caroline, New York, 3152",
    "enabled": false
  },
  {
    "name": "Johnston Brady",
    "phone": "+1 (993) 435-3377",
    "city": "Brantleyville",
    "address": "370 Ryerson Street, Manitou, California, 1062",
    "enabled": false
  },
  {
    "name": "Little Slater",
    "phone": "+1 (914) 539-3874",
    "city": "Springhill",
    "address": "233 Danforth Street, Knowlton, Palau, 2700",
    "enabled": true
  },
  {
    "name": "Enid Burt",
    "phone": "+1 (943) 431-3274",
    "city": "Shepardsville",
    "address": "294 Menahan Street, Soham, Idaho, 7413",
    "enabled": true
  },
  {
    "name": "Shauna Burns",
    "phone": "+1 (859) 576-2395",
    "city": "Chaparrito",
    "address": "592 Clove Road, Escondida, Florida, 902",
    "enabled": true
  },
  {
    "name": "Nona Fitzpatrick",
    "phone": "+1 (945) 521-2654",
    "city": "Statenville",
    "address": "367 Ebony Court, Dellview, Mississippi, 4517",
    "enabled": false
  },
  {
    "name": "Merritt Warren",
    "phone": "+1 (962) 438-2750",
    "city": "Hiko",
    "address": "487 Horace Court, Rehrersburg, North Carolina, 9800",
    "enabled": true
  },
  {
    "name": "Jackson Stewart",
    "phone": "+1 (948) 534-2129",
    "city": "Glidden",
    "address": "361 Thames Street, Castleton, Maryland, 6420",
    "enabled": true
  },
  {
    "name": "Hebert Payne",
    "phone": "+1 (869) 559-3028",
    "city": "Irwin",
    "address": "429 Utica Avenue, Gardners, Washington, 8909",
    "enabled": false
  },
  {
    "name": "Dunlap Dean",
    "phone": "+1 (824) 491-3990",
    "city": "Haena",
    "address": "828 Tennis Court, Newry, Arizona, 7789",
    "enabled": false
  },
  {
    "name": "Gillespie Bradford",
    "phone": "+1 (916) 569-2427",
    "city": "Tilden",
    "address": "367 Division Place, Brule, Hawaii, 2811",
    "enabled": true
  },
  {
    "name": "Stacy Chavez",
    "phone": "+1 (850) 558-3548",
    "city": "Stollings",
    "address": "287 Willmohr Street, Manila, Ohio, 3411",
    "enabled": true
  },
  {
    "name": "Briana Nguyen",
    "phone": "+1 (881) 413-3473",
    "city": "Valmy",
    "address": "651 Dictum Court, Fairforest, South Carolina, 5003",
    "enabled": false
  },
  {
    "name": "Kirkland Stevens",
    "phone": "+1 (957) 492-2810",
    "city": "Wollochet",
    "address": "419 Kingsland Avenue, Newcastle, South Dakota, 7126",
    "enabled": true
  },
  {
    "name": "Briggs Strong",
    "phone": "+1 (830) 483-2302",
    "city": "Jugtown",
    "address": "144 Jerome Avenue, Walland, Delaware, 7838",
    "enabled": false
  },
  {
    "name": "Owens Blevins",
    "phone": "+1 (800) 589-2755",
    "city": "Veguita",
    "address": "672 Harden Street, Thatcher, Nebraska, 143",
    "enabled": true
  },
  {
    "name": "Brandy Baxter",
    "phone": "+1 (906) 489-3460",
    "city": "Ivanhoe",
    "address": "993 Cumberland Street, Roulette, Pennsylvania, 5257",
    "enabled": true
  },
  {
    "name": "Cardenas Cortez",
    "phone": "+1 (933) 587-2157",
    "city": "Ahwahnee",
    "address": "973 Greenwood Avenue, Bellfountain, Louisiana, 4878",
    "enabled": false
  },
  {
    "name": "Battle Gibbs",
    "phone": "+1 (844) 416-2911",
    "city": "Kennedyville",
    "address": "816 Royce Street, Ironton, Arkansas, 9763",
    "enabled": true
  },
  {
    "name": "Celina Haynes",
    "phone": "+1 (936) 560-3791",
    "city": "Gadsden",
    "address": "688 Beaver Street, Felt, Marshall Islands, 3614",
    "enabled": true
  },
  {
    "name": "Farmer Wolf",
    "phone": "+1 (881) 581-2015",
    "city": "Wolcott",
    "address": "416 Hancock Street, Fedora, New Mexico, 2337",
    "enabled": false
  },
  {
    "name": "Victoria Martinez",
    "phone": "+1 (920) 532-2976",
    "city": "Bend",
    "address": "673 Lafayette Walk, Dixonville, Virginia, 8388",
    "enabled": true
  },
  {
    "name": "Marva Kaufman",
    "phone": "+1 (954) 551-2924",
    "city": "Rosewood",
    "address": "518 Exeter Street, Crown, Kentucky, 7565",
    "enabled": true
  },
  {
    "name": "Holland Watson",
    "phone": "+1 (813) 552-2710",
    "city": "Clarence",
    "address": "960 Meserole Avenue, Fivepointville, Massachusetts, 9645",
    "enabled": true
  },
  {
    "name": "Rosemarie Meadows",
    "phone": "+1 (939) 504-2520",
    "city": "Johnsonburg",
    "address": "297 Falmouth Street, Loomis, Iowa, 5848",
    "enabled": false
  },
  {
    "name": "Harrison Luna",
    "phone": "+1 (960) 438-2558",
    "city": "Gracey",
    "address": "109 Pine Street, Greenbush, Virgin Islands, 7010",
    "enabled": false
  },
  {
    "name": "Mendez Barnes",
    "phone": "+1 (997) 490-2376",
    "city": "Brazos",
    "address": "948 Hill Street, Conestoga, Texas, 6341",
    "enabled": false
  },
  {
    "name": "Leanne Whitehead",
    "phone": "+1 (954) 527-3898",
    "city": "Floriston",
    "address": "821 Bushwick Place, Cutter, Wyoming, 9619",
    "enabled": false
  },
  {
    "name": "Lenore Vincent",
    "phone": "+1 (843) 564-2278",
    "city": "Riceville",
    "address": "430 Joralemon Street, Dundee, North Dakota, 1071",
    "enabled": true
  },
  {
    "name": "Burns Lott",
    "phone": "+1 (926) 446-3858",
    "city": "Campo",
    "address": "459 Verona Street, Swartzville, Minnesota, 849",
    "enabled": false
  },
  {
    "name": "Slater Lowe",
    "phone": "+1 (912) 580-3753",
    "city": "Wells",
    "address": "856 Locust Street, Volta, Connecticut, 180",
    "enabled": false
  },
  {
    "name": "Malinda Pennington",
    "phone": "+1 (990) 453-3509",
    "city": "Talpa",
    "address": "383 Anna Court, Ilchester, Oklahoma, 3691",
    "enabled": true
  },
  {
    "name": "Vazquez Mclaughlin",
    "phone": "+1 (957) 483-2166",
    "city": "Clara",
    "address": "289 Guider Avenue, Sanders, District Of Columbia, 5694",
    "enabled": true
  },
  {
    "name": "Collier Hoffman",
    "phone": "+1 (916) 482-3452",
    "city": "Limestone",
    "address": "858 Noel Avenue, Sedley, Kansas, 5932",
    "enabled": true
  },
  {
    "name": "Blanche Bates",
    "phone": "+1 (946) 548-2087",
    "city": "Weogufka",
    "address": "378 Elmwood Avenue, Stewart, Vermont, 4930",
    "enabled": true
  },
  {
    "name": "Latoya Oneal",
    "phone": "+1 (802) 426-2816",
    "city": "Dowling",
    "address": "528 Cheever Place, Calvary, Maine, 4644",
    "enabled": true
  },
  {
    "name": "Weiss Zimmerman",
    "phone": "+1 (925) 492-2933",
    "city": "Machias",
    "address": "953 Arion Place, Murillo, Oregon, 796",
    "enabled": true
  },
  {
    "name": "Molina Turner",
    "phone": "+1 (940) 420-3196",
    "city": "Kipp",
    "address": "250 Argyle Road, Gardiner, Georgia, 7173",
    "enabled": true
  },
  {
    "name": "Moreno Singleton",
    "phone": "+1 (905) 556-3392",
    "city": "Alderpoint",
    "address": "839 Stockton Street, Holtville, Alaska, 5504",
    "enabled": false
  },
  {
    "name": "Lucas Miller",
    "phone": "+1 (835) 556-3460",
    "city": "Yettem",
    "address": "785 Cedar Street, Chautauqua, New Jersey, 2092",
    "enabled": false
  },
  {
    "name": "Alice Nielsen",
    "phone": "+1 (836) 514-3591",
    "city": "Jennings",
    "address": "915 Eckford Street, Como, Rhode Island, 8118",
    "enabled": false
  },
  {
    "name": "Mari Anderson",
    "phone": "+1 (820) 595-3309",
    "city": "Jacumba",
    "address": "869 Beach Place, Clayville, Federated States Of Micronesia, 9877",
    "enabled": false
  },
  {
    "name": "Betty Branch",
    "phone": "+1 (998) 401-2315",
    "city": "Devon",
    "address": "693 Terrace Place, Deputy, Alabama, 5517",
    "enabled": true
  },
  {
    "name": "Mollie Allison",
    "phone": "+1 (882) 591-2191",
    "city": "Tonopah",
    "address": "887 Llama Court, Keyport, Puerto Rico, 9306",
    "enabled": true
  },
  {
    "name": "Morgan Harding",
    "phone": "+1 (802) 448-2990",
    "city": "Franklin",
    "address": "134 Matthews Court, Vowinckel, Michigan, 8376",
    "enabled": true
  },
  {
    "name": "Leona Barry",
    "phone": "+1 (800) 496-2490",
    "city": "Sperryville",
    "address": "892 Cooper Street, Kenvil, American Samoa, 3593",
    "enabled": true
  },
  {
    "name": "Stark Ramirez",
    "phone": "+1 (925) 574-2266",
    "city": "Leyner",
    "address": "195 Schenck Court, Umapine, Illinois, 5553",
    "enabled": false
  },
  {
    "name": "Beverly Velazquez",
    "phone": "+1 (891) 510-3076",
    "city": "Defiance",
    "address": "886 Vanderbilt Street, Kanauga, Colorado, 9785",
    "enabled": false
  },
  {
    "name": "Katheryn Blankenship",
    "phone": "+1 (950) 438-3597",
    "city": "Martinez",
    "address": "426 Hinckley Place, Hegins, Northern Mariana Islands, 9635",
    "enabled": true
  },
  {
    "name": "Debora Walker",
    "phone": "+1 (867) 550-3453",
    "city": "Manchester",
    "address": "815 Allen Avenue, Delco, Montana, 9130",
    "enabled": true
  },
  {
    "name": "Huffman Ratliff",
    "phone": "+1 (979) 444-3867",
    "city": "Idamay",
    "address": "841 Vandalia Avenue, Bartonsville, Utah, 5958",
    "enabled": false
  },
  {
    "name": "Shannon Stafford",
    "phone": "+1 (979) 587-2156",
    "city": "Singer",
    "address": "137 Frank Court, Richford, Guam, 452",
    "enabled": true
  },
  {
    "name": "Courtney Guerra",
    "phone": "+1 (911) 542-3804",
    "city": "Islandia",
    "address": "617 Nelson Street, Verdi, Tennessee, 1299",
    "enabled": true
  },
  {
    "name": "Armstrong Scott",
    "phone": "+1 (965) 509-2667",
    "city": "Kaka",
    "address": "265 Rockwell Place, Fairmount, Nevada, 9613",
    "enabled": false
  },
  {
    "name": "Mcintyre Black",
    "phone": "+1 (975) 546-2714",
    "city": "Gratton",
    "address": "286 Conklin Avenue, Fillmore, Indiana, 2864",
    "enabled": false
  },
  {
    "name": "Sophie Zamora",
    "phone": "+1 (922) 588-2221",
    "city": "Malo",
    "address": "237 Goodwin Place, Wanship, New Hampshire, 5961",
    "enabled": false
  },
  {
    "name": "Kelly Hartman",
    "phone": "+1 (915) 509-2002",
    "city": "Yukon",
    "address": "341 Eaton Court, Bennett, West Virginia, 7460",
    "enabled": true
  },
  {
    "name": "Jessica Dominguez",
    "phone": "+1 (888) 449-3067",
    "city": "Wanamie",
    "address": "681 Jamison Lane, Holcombe, Wisconsin, 6144",
    "enabled": false
  },
  {
    "name": "Kathleen Conrad",
    "phone": "+1 (992) 521-2395",
    "city": "Bath",
    "address": "371 Elm Place, Westerville, New York, 6582",
    "enabled": false
  },
  {
    "name": "Valenzuela Burks",
    "phone": "+1 (840) 400-2705",
    "city": "Hobucken",
    "address": "914 Suydam Place, Gilmore, California, 269",
    "enabled": true
  },
  {
    "name": "Wolfe Frost",
    "phone": "+1 (840) 448-2554",
    "city": "Moraida",
    "address": "553 Mill Avenue, Bonanza, Palau, 9053",
    "enabled": true
  },
  {
    "name": "Kelsey Dudley",
    "phone": "+1 (905) 561-3635",
    "city": "Trucksville",
    "address": "697 Winthrop Street, Wintersburg, Idaho, 6619",
    "enabled": true
  },
  {
    "name": "Townsend Dillard",
    "phone": "+1 (838) 599-3620",
    "city": "Basye",
    "address": "520 Creamer Street, Yogaville, Florida, 9990",
    "enabled": true
  },
  {
    "name": "Gilliam Mccray",
    "phone": "+1 (812) 425-2364",
    "city": "Osage",
    "address": "970 Keap Street, Trinway, Mississippi, 7426",
    "enabled": true
  },
  {
    "name": "Powell Yang",
    "phone": "+1 (968) 572-3931",
    "city": "Topanga",
    "address": "972 Vernon Avenue, Dale, North Carolina, 2033",
    "enabled": true
  },
  {
    "name": "Adeline Decker",
    "phone": "+1 (820) 560-3769",
    "city": "Sabillasville",
    "address": "147 Bayview Avenue, Emerald, Maryland, 9844",
    "enabled": true
  },
  {
    "name": "Shanna Moran",
    "phone": "+1 (908) 417-2657",
    "city": "Drummond",
    "address": "672 Louis Place, Cavalero, Washington, 8147",
    "enabled": false
  },
  {
    "name": "Steele Page",
    "phone": "+1 (902) 469-2344",
    "city": "Connerton",
    "address": "620 Mersereau Court, Templeton, Arizona, 4874",
    "enabled": false
  },
  {
    "name": "Knowles Barton",
    "phone": "+1 (925) 541-2760",
    "city": "Cuylerville",
    "address": "128 Schaefer Street, Wilmington, Hawaii, 7852",
    "enabled": true
  },
  {
    "name": "Jennifer Guerrero",
    "phone": "+1 (894) 490-3770",
    "city": "Sandston",
    "address": "409 Bills Place, Rosedale, Ohio, 9805",
    "enabled": true
  },
  {
    "name": "Wooten Benson",
    "phone": "+1 (877) 600-3909",
    "city": "Carbonville",
    "address": "970 Village Road, Henrietta, South Carolina, 5832",
    "enabled": true
  },
  {
    "name": "Gould Ayala",
    "phone": "+1 (936) 556-2058",
    "city": "Sanford",
    "address": "701 Otsego Street, Sussex, South Dakota, 3452",
    "enabled": false
  },
  {
    "name": "Sparks Jacobson",
    "phone": "+1 (885) 553-3584",
    "city": "Forbestown",
    "address": "326 Stryker Street, Gibsonia, Delaware, 482",
    "enabled": true
  },
  {
    "name": "Latisha Morin",
    "phone": "+1 (871) 509-3933",
    "city": "Brookfield",
    "address": "234 Colin Place, Nipinnawasee, Nebraska, 5920",
    "enabled": true
  },
  {
    "name": "Oneill Kent",
    "phone": "+1 (887) 572-3123",
    "city": "Bancroft",
    "address": "798 Montrose Avenue, Zortman, Pennsylvania, 2718",
    "enabled": true
  },
  {
    "name": "Dominguez Stein",
    "phone": "+1 (847) 439-3358",
    "city": "Konterra",
    "address": "379 Martense Street, Glenbrook, Louisiana, 9142",
    "enabled": false
  },
  {
    "name": "Dunn Nichols",
    "phone": "+1 (814) 555-2010",
    "city": "Gloucester",
    "address": "184 Coffey Street, Summertown, Arkansas, 6573",
    "enabled": true
  },
  {
    "name": "Tiffany Lynch",
    "phone": "+1 (862) 506-3039",
    "city": "Kiskimere",
    "address": "528 Willow Place, Delshire, Marshall Islands, 908",
    "enabled": false
  },
  {
    "name": "Shelton Merrill",
    "phone": "+1 (963) 579-2890",
    "city": "Tryon",
    "address": "713 Johnson Street, Finzel, New Mexico, 9779",
    "enabled": true
  },
  {
    "name": "Karla Mccarty",
    "phone": "+1 (890) 551-2897",
    "city": "Austinburg",
    "address": "112 Evans Street, Columbus, Virginia, 7831",
    "enabled": false
  },
  {
    "name": "Chavez Hendrix",
    "phone": "+1 (842) 450-3821",
    "city": "Tecolotito",
    "address": "240 Story Street, Hiseville, Kentucky, 9412",
    "enabled": false
  },
  {
    "name": "Kim Wolfe",
    "phone": "+1 (848) 593-3307",
    "city": "Berwind",
    "address": "239 Applegate Court, Oley, Massachusetts, 7422",
    "enabled": true
  },
  {
    "name": "Shields Mcbride",
    "phone": "+1 (804) 561-2805",
    "city": "Boyd",
    "address": "738 Tabor Court, Lydia, Iowa, 829",
    "enabled": false
  },
  {
    "name": "Elizabeth Warner",
    "phone": "+1 (955) 507-2227",
    "city": "Bellamy",
    "address": "603 Rodney Street, Worton, Virgin Islands, 1646",
    "enabled": false
  },
  {
    "name": "Dawson Noble",
    "phone": "+1 (903) 516-3211",
    "city": "Newkirk",
    "address": "130 Interborough Parkway, Bakersville, Texas, 4762",
    "enabled": true
  },
  {
    "name": "Natalie Koch",
    "phone": "+1 (957) 592-2850",
    "city": "Riviera",
    "address": "612 Lott Place, Faxon, Wyoming, 5748",
    "enabled": false
  },
  {
    "name": "Payne Elliott",
    "phone": "+1 (999) 558-2277",
    "city": "Bentonville",
    "address": "462 National Drive, Jamestown, North Dakota, 1117",
    "enabled": false
  },
  {
    "name": "Kitty Glover",
    "phone": "+1 (939) 580-2453",
    "city": "Blairstown",
    "address": "241 Dahl Court, Albany, Minnesota, 4833",
    "enabled": true
  },
  {
    "name": "Lupe Wilkerson",
    "phone": "+1 (980) 509-3111",
    "city": "Orovada",
    "address": "966 Brooklyn Road, Needmore, Connecticut, 3417",
    "enabled": true
  },
  {
    "name": "Callahan Rogers",
    "phone": "+1 (998) 410-3629",
    "city": "Baker",
    "address": "875 Tudor Terrace, Blodgett, Oklahoma, 2097",
    "enabled": false
  },
  {
    "name": "Richardson Colon",
    "phone": "+1 (879) 513-3140",
    "city": "Balm",
    "address": "188 Richards Street, Soudan, District Of Columbia, 7219",
    "enabled": false
  },
  {
    "name": "Elsa Sullivan",
    "phone": "+1 (949) 600-3975",
    "city": "Zarephath",
    "address": "162 Lake Avenue, Thermal, Kansas, 1428",
    "enabled": false
  },
  {
    "name": "Rhea Dixon",
    "phone": "+1 (864) 411-2968",
    "city": "Tilleda",
    "address": "596 Portland Avenue, Vallonia, Vermont, 413",
    "enabled": false
  },
  {
    "name": "Guy Rowland",
    "phone": "+1 (959) 445-2892",
    "city": "Bourg",
    "address": "271 Varet Street, Eastvale, Maine, 9978",
    "enabled": false
  },
  {
    "name": "Alison Chang",
    "phone": "+1 (993) 431-3926",
    "city": "Shrewsbury",
    "address": "756 Apollo Street, Dunbar, Oregon, 1124",
    "enabled": false
  },
  {
    "name": "Cameron Stark",
    "phone": "+1 (879) 424-3425",
    "city": "Finderne",
    "address": "881 Elliott Walk, Disautel, Georgia, 6755",
    "enabled": false
  },
  {
    "name": "Maddox Jensen",
    "phone": "+1 (868) 507-2401",
    "city": "Interlochen",
    "address": "919 Irwin Street, Aguila, Alaska, 2348",
    "enabled": true
  },
  {
    "name": "Cornelia Shaffer",
    "phone": "+1 (820) 546-3070",
    "city": "Stevens",
    "address": "765 Rapelye Street, Elizaville, New Jersey, 6780",
    "enabled": true
  },
  {
    "name": "Lena Horton",
    "phone": "+1 (831) 477-3924",
    "city": "Bendon",
    "address": "684 Ralph Avenue, Darlington, Rhode Island, 3229",
    "enabled": true
  },
  {
    "name": "Sasha Briggs",
    "phone": "+1 (886) 498-2645",
    "city": "Hondah",
    "address": "499 Hanson Place, Gambrills, Federated States Of Micronesia, 1431",
    "enabled": false
  },
  {
    "name": "Jones Gill",
    "phone": "+1 (819) 471-3638",
    "city": "Eagleville",
    "address": "989 Gunnison Court, Broadlands, Alabama, 3999",
    "enabled": true
  },
  {
    "name": "Tasha Ray",
    "phone": "+1 (945) 435-2582",
    "city": "Century",
    "address": "609 Calder Place, Dubois, Puerto Rico, 2829",
    "enabled": false
  },
  {
    "name": "Montgomery Brown",
    "phone": "+1 (953) 474-3480",
    "city": "Clarksburg",
    "address": "376 Mayfair Drive, Thomasville, Michigan, 2593",
    "enabled": true
  },
  {
    "name": "Buckley Tyler",
    "phone": "+1 (896) 447-3955",
    "city": "Belva",
    "address": "601 Chauncey Street, Watrous, American Samoa, 1018",
    "enabled": false
  },
  {
    "name": "Neal Puckett",
    "phone": "+1 (857) 583-2021",
    "city": "Fostoria",
    "address": "211 Ingraham Street, Virgie, Illinois, 1732",
    "enabled": true
  },
  {
    "name": "Haley Hatfield",
    "phone": "+1 (848) 464-3838",
    "city": "Sultana",
    "address": "548 Cobek Court, Juarez, Colorado, 3478",
    "enabled": true
  },
  {
    "name": "Zamora Obrien",
    "phone": "+1 (851) 455-3557",
    "city": "Allensworth",
    "address": "942 Bayard Street, Charco, Northern Mariana Islands, 8848",
    "enabled": false
  },
  {
    "name": "Bush Wilcox",
    "phone": "+1 (979) 402-2388",
    "city": "Babb",
    "address": "556 Knickerbocker Avenue, Cliff, Montana, 5980",
    "enabled": false
  },
  {
    "name": "Polly Kramer",
    "phone": "+1 (849) 459-3003",
    "city": "Ripley",
    "address": "409 Lefferts Avenue, Suitland, Utah, 7446",
    "enabled": false
  },
  {
    "name": "Doris Robertson",
    "phone": "+1 (980) 530-2924",
    "city": "Motley",
    "address": "234 Narrows Avenue, Iberia, Guam, 4808",
    "enabled": false
  },
  {
    "name": "Cote Clayton",
    "phone": "+1 (964) 528-3337",
    "city": "Freeburn",
    "address": "571 Graham Avenue, Leola, Tennessee, 5006",
    "enabled": false
  },
  {
    "name": "Joyce Stephenson",
    "phone": "+1 (906) 470-2176",
    "city": "Layhill",
    "address": "140 Polar Street, Waterview, Nevada, 2894",
    "enabled": false
  },
  {
    "name": "Audra Lee",
    "phone": "+1 (895) 517-3320",
    "city": "Chicopee",
    "address": "305 Powers Street, Eastmont, Indiana, 462",
    "enabled": false
  },
  {
    "name": "Mckinney Everett",
    "phone": "+1 (927) 567-2886",
    "city": "Fairview",
    "address": "524 Norman Avenue, Englevale, New Hampshire, 5498",
    "enabled": true
  },
  {
    "name": "Humphrey Fulton",
    "phone": "+1 (972) 599-3519",
    "city": "Gorst",
    "address": "162 Melrose Street, Freelandville, West Virginia, 4135",
    "enabled": true
  },
  {
    "name": "Ryan Reed",
    "phone": "+1 (881) 404-2096",
    "city": "Foxworth",
    "address": "506 Herkimer Place, Shelby, Wisconsin, 3710",
    "enabled": false
  },
  {
    "name": "Edna Rasmussen",
    "phone": "+1 (854) 451-3039",
    "city": "Day",
    "address": "537 Aitken Place, Reno, New York, 5207",
    "enabled": false
  },
  {
    "name": "Aimee Hull",
    "phone": "+1 (932) 495-3295",
    "city": "Darbydale",
    "address": "385 Conduit Boulevard, Belvoir, California, 4494",
    "enabled": false
  },
  {
    "name": "Earline Saunders",
    "phone": "+1 (952) 560-2665",
    "city": "Germanton",
    "address": "548 Aurelia Court, Seymour, Palau, 1978",
    "enabled": true
  },
  {
    "name": "Nichols Rollins",
    "phone": "+1 (966) 401-2876",
    "city": "Bainbridge",
    "address": "171 Euclid Avenue, Sattley, Idaho, 9038",
    "enabled": true
  },
  {
    "name": "Gamble Gordon",
    "phone": "+1 (823) 541-2878",
    "city": "Orviston",
    "address": "124 Church Lane, Hachita, Florida, 3447",
    "enabled": false
  },
  {
    "name": "Brennan Mueller",
    "phone": "+1 (950) 596-2500",
    "city": "Kerby",
    "address": "626 Ashford Street, Bethany, Mississippi, 1259",
    "enabled": true
  },
  {
    "name": "Glass Holt",
    "phone": "+1 (871) 452-3967",
    "city": "Jacksonwald",
    "address": "674 Gain Court, Laurelton, North Carolina, 936",
    "enabled": true
  },
  {
    "name": "Sondra Marquez",
    "phone": "+1 (988) 509-2228",
    "city": "Norwood",
    "address": "820 Vanderveer Street, Russellville, Maryland, 6117",
    "enabled": true
  },
  {
    "name": "Haynes Alexander",
    "phone": "+1 (815) 403-2146",
    "city": "Ogema",
    "address": "581 Sharon Street, Calverton, Washington, 4127",
    "enabled": true
  },
  {
    "name": "Cooke Orr",
    "phone": "+1 (946) 480-3343",
    "city": "Garnet",
    "address": "770 Sunnyside Avenue, Spelter, Arizona, 967",
    "enabled": true
  },
  {
    "name": "Snider Parrish",
    "phone": "+1 (849) 444-3961",
    "city": "Nicut",
    "address": "163 Bethel Loop, Snyderville, Hawaii, 3579",
    "enabled": true
  },
  {
    "name": "Eleanor Cain",
    "phone": "+1 (913) 499-2605",
    "city": "Urbana",
    "address": "768 Bradford Street, Fowlerville, Ohio, 411",
    "enabled": true
  },
  {
    "name": "Marguerite Ryan",
    "phone": "+1 (904) 419-3375",
    "city": "Lindcove",
    "address": "109 Lawn Court, Summerfield, South Carolina, 2820",
    "enabled": true
  },
  {
    "name": "Hilary Frye",
    "phone": "+1 (979) 436-2355",
    "city": "Maxville",
    "address": "725 Schenectady Avenue, Homeworth, South Dakota, 1299",
    "enabled": false
  },
  {
    "name": "Luna Simon",
    "phone": "+1 (820) 453-2446",
    "city": "Beyerville",
    "address": "912 Havemeyer Street, Lynn, Delaware, 6827",
    "enabled": false
  },
  {
    "name": "Anastasia Daniels",
    "phone": "+1 (902) 528-2065",
    "city": "Gibbsville",
    "address": "542 Kosciusko Street, Oneida, Nebraska, 1677",
    "enabled": false
  },
  {
    "name": "Laurie Brock",
    "phone": "+1 (943) 504-2915",
    "city": "Beaverdale",
    "address": "570 Bevy Court, Choctaw, Pennsylvania, 9660",
    "enabled": true
  },
  {
    "name": "Marissa Duffy",
    "phone": "+1 (928) 581-2455",
    "city": "Rushford",
    "address": "906 Morgan Avenue, Marion, Louisiana, 3339",
    "enabled": true
  },
  {
    "name": "Fran Quinn",
    "phone": "+1 (847) 537-2320",
    "city": "Topaz",
    "address": "477 Victor Road, Wacissa, Arkansas, 938",
    "enabled": false
  },
  {
    "name": "Wheeler Kelley",
    "phone": "+1 (987) 402-2127",
    "city": "Edneyville",
    "address": "553 Grace Court, Ellerslie, Marshall Islands, 7831",
    "enabled": true
  },
  {
    "name": "Maynard Vazquez",
    "phone": "+1 (978) 571-3979",
    "city": "Gulf",
    "address": "154 Wyckoff Street, Brownlee, New Mexico, 7508",
    "enabled": true
  },
  {
    "name": "Lambert Barber",
    "phone": "+1 (810) 519-3021",
    "city": "Crisman",
    "address": "561 Willoughby Avenue, Snelling, Virginia, 7481",
    "enabled": true
  },
  {
    "name": "Esmeralda Dorsey",
    "phone": "+1 (838) 474-3477",
    "city": "Echo",
    "address": "811 Barbey Street, Wiscon, Kentucky, 6816",
    "enabled": true
  },
  {
    "name": "Sutton Herrera",
    "phone": "+1 (943) 442-3584",
    "city": "Hiwasse",
    "address": "170 Billings Place, Chical, Massachusetts, 7356",
    "enabled": false
  },
  {
    "name": "Alicia Bishop",
    "phone": "+1 (862) 455-2235",
    "city": "Flintville",
    "address": "579 Ocean Court, Cazadero, Iowa, 3598",
    "enabled": true
  },
  {
    "name": "Smith Jarvis",
    "phone": "+1 (929) 482-2537",
    "city": "Maybell",
    "address": "652 Nostrand Avenue, Washington, Virgin Islands, 4386",
    "enabled": false
  },
  {
    "name": "Edwards Kirk",
    "phone": "+1 (876) 507-3384",
    "city": "Woodruff",
    "address": "450 Belmont Avenue, Somerset, Texas, 8089",
    "enabled": true
  },
  {
    "name": "Pugh Newton",
    "phone": "+1 (944) 480-2826",
    "city": "Enlow",
    "address": "588 Coventry Road, Blende, Wyoming, 5266",
    "enabled": true
  },
  {
    "name": "Aline Franco",
    "phone": "+1 (963) 425-3729",
    "city": "Homeland",
    "address": "899 Hale Avenue, Lisco, North Dakota, 9709",
    "enabled": true
  },
  {
    "name": "Mosley Pate",
    "phone": "+1 (816) 419-3931",
    "city": "Tedrow",
    "address": "425 Eagle Street, Steinhatchee, Minnesota, 1891",
    "enabled": false
  },
  {
    "name": "Joann Booth",
    "phone": "+1 (921) 411-3362",
    "city": "Garfield",
    "address": "827 Newton Street, Tioga, Connecticut, 537",
    "enabled": true
  },
  {
    "name": "Meyer Wilkinson",
    "phone": "+1 (804) 421-2504",
    "city": "Trona",
    "address": "887 Manhattan Avenue, Hamilton, Oklahoma, 5832",
    "enabled": true
  },
  {
    "name": "Lane Christensen",
    "phone": "+1 (907) 594-3336",
    "city": "Concho",
    "address": "473 Degraw Street, Linganore, District Of Columbia, 5373",
    "enabled": true
  },
  {
    "name": "Shaw Nash",
    "phone": "+1 (971) 583-2977",
    "city": "Darrtown",
    "address": "207 Moore Place, Callaghan, Kansas, 191",
    "enabled": true
  },
  {
    "name": "Bobbie Vega",
    "phone": "+1 (947) 528-2067",
    "city": "Waikele",
    "address": "889 Stuyvesant Avenue, Alamo, Vermont, 8212",
    "enabled": true
  },
  {
    "name": "Lourdes Simpson",
    "phone": "+1 (801) 454-3723",
    "city": "Evergreen",
    "address": "815 Onderdonk Avenue, Brewster, Maine, 6343",
    "enabled": false
  },
  {
    "name": "Chandler Michael",
    "phone": "+1 (871) 556-3174",
    "city": "Smock",
    "address": "463 Seeley Street, Ola, Oregon, 824",
    "enabled": true
  },
  {
    "name": "Nichole Logan",
    "phone": "+1 (951) 557-2516",
    "city": "Dola",
    "address": "481 Lefferts Place, Teasdale, Georgia, 448",
    "enabled": false
  },
  {
    "name": "Mcgee Mcmahon",
    "phone": "+1 (900) 583-2895",
    "city": "Sunriver",
    "address": "256 Brighton Avenue, Kimmell, Alaska, 6127",
    "enabled": false
  },
  {
    "name": "Wilson Peck",
    "phone": "+1 (864) 451-2829",
    "city": "Bladensburg",
    "address": "662 Broadway , Sardis, New Jersey, 6140",
    "enabled": false
  },
  {
    "name": "Michael Kidd",
    "phone": "+1 (872) 538-3764",
    "city": "Nile",
    "address": "523 Locust Avenue, Allentown, Rhode Island, 1881",
    "enabled": true
  },
  {
    "name": "Vega Mullins",
    "phone": "+1 (913) 597-2790",
    "city": "Vandiver",
    "address": "930 Hope Street, Herbster, Federated States Of Micronesia, 9243",
    "enabled": true
  },
  {
    "name": "Nikki Rosa",
    "phone": "+1 (818) 546-3055",
    "city": "Mulino",
    "address": "803 Riverdale Avenue, Driftwood, Alabama, 886",
    "enabled": false
  },
  {
    "name": "Opal Hines",
    "phone": "+1 (934) 553-2514",
    "city": "Abrams",
    "address": "398 Gold Street, Greenfields, Puerto Rico, 7222",
    "enabled": true
  },
  {
    "name": "Tessa Maddox",
    "phone": "+1 (938) 596-2704",
    "city": "Woodlands",
    "address": "551 Pilling Street, Rodanthe, Michigan, 5175",
    "enabled": false
  },
  {
    "name": "Mallory Rhodes",
    "phone": "+1 (980) 533-3810",
    "city": "Taft",
    "address": "691 Ruby Street, Springdale, American Samoa, 936",
    "enabled": false
  },
  {
    "name": "Juliette Oneill",
    "phone": "+1 (803) 485-2239",
    "city": "Crucible",
    "address": "777 Portal Street, Stockdale, Illinois, 4461",
    "enabled": false
  },
  {
    "name": "Patton Hill",
    "phone": "+1 (918) 457-2874",
    "city": "Cotopaxi",
    "address": "918 Garnet Street, Aberdeen, Colorado, 1678",
    "enabled": false
  },
  {
    "name": "Nunez Buckley",
    "phone": "+1 (882) 449-2486",
    "city": "Groveville",
    "address": "817 Kiely Place, Maury, Northern Mariana Islands, 6361",
    "enabled": false
  },
  {
    "name": "Vasquez Serrano",
    "phone": "+1 (876) 410-2421",
    "city": "Condon",
    "address": "451 Amboy Street, Coultervillle, Montana, 749",
    "enabled": false
  },
  {
    "name": "Jerry Thomas",
    "phone": "+1 (960) 445-2943",
    "city": "Klagetoh",
    "address": "599 Albee Square, Terlingua, Utah, 9267",
    "enabled": false
  },
  {
    "name": "Hoffman Fuentes",
    "phone": "+1 (958) 567-3105",
    "city": "Whitmer",
    "address": "580 Voorhies Avenue, Fresno, Guam, 2226",
    "enabled": true
  },
  {
    "name": "Brady Mccoy",
    "phone": "+1 (972) 578-3611",
    "city": "Biehle",
    "address": "337 Hart Street, Lacomb, Tennessee, 4611",
    "enabled": false
  }
]