[
  {
    "CompanyName": "Isologix Zerology",
    "ContactName": "Daniels",
    "ContactTitle": "Mr.",
    "EmergencyMobile": 9123838998,
    "Phone": 211507850,
    "Enabled": true,
    "Fax": "Fax-71091",
    "Address": "Turnbull Avenue",
    "Country": "Paraguay",
    "City": "Orick",
    "Region": "Massachusetts",
    "PostalCode": 33033419
  },
  {
    "CompanyName": "Talkola Malathion",
    "ContactName": "Blackburn",
    "ContactTitle": "Mr.",
    "EmergencyMobile": 9124089928,
    "Phone": 212254309,
    "Enabled": true,
    "Fax": "Fax-55385",
    "Address": "Debevoise Street",
    "Country": "Ethiopia",
    "City": "Stollings",
    "Region": "Guam",
    "PostalCode": 33030785
  },
  {
    "CompanyName": "Isologics Exoteric",
    "ContactName": "Farrell",
    "ContactTitle": "Mr.",
    "EmergencyMobile": 9125921797,
    "Phone": 211889999,
    "Enabled": true,
    "Fax": "Fax-64428",
    "Address": "Woods Place",
    "Country": "Guinea",
    "City": "Orovada",
    "Region": "Oregon",
    "PostalCode": 54034898
  },
  {
    "CompanyName": "Zilidium Ezent",
    "ContactName": "Merritt",
    "ContactTitle": "Mr.",
    "EmergencyMobile": 9123461441,
    "Phone": 212518237,
    "Enabled": true,
    "Fax": "Fax-52810",
    "Address": "Lacon Court",
    "Country": "Saint Vincent and The Grenadines",
    "City": "Morriston",
    "Region": "Montana",
    "PostalCode": 42409140
  },
  {
    "CompanyName": "Ecratic Visualix",
    "ContactName": "Rosales",
    "ContactTitle": "Mr.",
    "EmergencyMobile": 9124444005,
    "Phone": 219981769,
    "Enabled": true,
    "Fax": "Fax-83551",
    "Address": "Downing Street",
    "Country": "Costa Rica",
    "City": "Castleton",
    "Region": "Florida",
    "PostalCode": 52257701
  },
  {
    "CompanyName": "Paragonia Lovepad",
    "ContactName": "Maldonado",
    "ContactTitle": "Mr.",
    "EmergencyMobile": 9127872885,
    "Phone": 211143755,
    "Enabled": true,
    "Fax": "Fax-86094",
    "Address": "Sumpter Street",
    "Country": "Russian Federation",
    "City": "Goochland",
    "Region": "Missouri",
    "PostalCode": 82603403
  },
  {
    "CompanyName": "Waab Comcur",
    "ContactName": "Ramirez",
    "ContactTitle": "Mr.",
    "EmergencyMobile": 9128330901,
    "Phone": 216478224,
    "Enabled": true,
    "Fax": "Fax-80287",
    "Address": "Varanda Place",
    "Country": "Gibraltar",
    "City": "Windsor",
    "Region": "Ohio",
    "PostalCode": 70866469
  },
  {
    "CompanyName": "Cipromox Dentrex",
    "ContactName": "Griffith",
    "ContactTitle": "Mr.",
    "EmergencyMobile": 9124412085,
    "Phone": 212983722,
    "Enabled": true,
    "Fax": "Fax-39118",
    "Address": "Bayard Street",
    "Country": "Equatorial Guinea",
    "City": "Allentown",
    "Region": "Rhode Island",
    "PostalCode": 61711701
  },
  {
    "CompanyName": "Irack Datagen",
    "ContactName": "Sweeney",
    "ContactTitle": "Mr.",
    "EmergencyMobile": 9128188557,
    "Phone": 211720903,
    "Enabled": true,
    "Fax": "Fax-27060",
    "Address": "Pine Street",
    "Country": "Brazil",
    "City": "Fedora",
    "Region": "Iowa",
    "PostalCode": 68274848
  },
  {
    "CompanyName": "Zosis Pyramia",
    "ContactName": "Acevedo",
    "ContactTitle": "Mr.",
    "EmergencyMobile": 9125664540,
    "Phone": 214195896,
    "Enabled": true,
    "Fax": "Fax-62634",
    "Address": "Ocean Parkway",
    "Country": "Cameroon",
    "City": "Takilma",
    "Region": "New York",
    "PostalCode": 12579014
  },
  {
    "CompanyName": "Comtext Dognost",
    "ContactName": "Fletcher",
    "ContactTitle": "Mr.",
    "EmergencyMobile": 9127897275,
    "Phone": 211419531,
    "Enabled": true,
    "Fax": "Fax-45789",
    "Address": "Dictum Court",
    "Country": "Switzerland",
    "City": "Walton",
    "Region": "Virginia",
    "PostalCode": 39908594
  },
  {
    "CompanyName": "Marqet Isologia",
    "ContactName": "Ware",
    "ContactTitle": "Mr.",
    "EmergencyMobile": 912541625,
    "Phone": 212929935,
    "Enabled": true,
    "Fax": "Fax-33174",
    "Address": "Kaufman Place",
    "Country": "Angola",
    "City": "Thynedale",
    "Region": "American Samoa",
    "PostalCode": 19394014
  },
  {
    "CompanyName": "Valreda Ecraze",
    "ContactName": "Nicholson",
    "ContactTitle": "Mr.",
    "EmergencyMobile": 9125322086,
    "Phone": 212447491,
    "Enabled": true,
    "Fax": "Fax-67583",
    "Address": "Onderdonk Avenue",
    "Country": "Venezuela",
    "City": "Blende",
    "Region": "Maine",
    "PostalCode": 4955188
  },
  {
    "CompanyName": "Buzzworks Ginkle",
    "ContactName": "Pace",
    "ContactTitle": "Mr.",
    "EmergencyMobile": 9125363581,
    "Phone": 21443515,
    "Enabled": true,
    "Fax": "Fax-44240",
    "Address": "Holly Street",
    "Country": "Macau",
    "City": "Riegelwood",
    "Region": "Nebraska",
    "PostalCode": 82296748
  },
  {
    "CompanyName": "Rameon Phuel",
    "ContactName": "Matthews",
    "ContactTitle": "Mr.",
    "EmergencyMobile": 9124702575,
    "Phone": 214431676,
    "Enabled": true,
    "Fax": "Fax-82680",
    "Address": "Brightwater Court",
    "Country": "Hungary",
    "City": "Kempton",
    "Region": "Puerto Rico",
    "PostalCode": 96343754
  },
  {
    "CompanyName": "Zepitope Signity",
    "ContactName": "Heath",
    "ContactTitle": "Mr.",
    "EmergencyMobile": 9122233160,
    "Phone": 212690150,
    "Enabled": true,
    "Fax": "Fax-44179",
    "Address": "Clinton Street",
    "Country": "Kenya",
    "City": "Martinez",
    "Region": "South Dakota",
    "PostalCode": 59238743
  },
  {
    "CompanyName": "Egypto Bovis",
    "ContactName": "Dale",
    "ContactTitle": "Mr.",
    "EmergencyMobile": 9121596068,
    "Phone": 215463681,
    "Enabled": true,
    "Fax": "Fax-23137",
    "Address": "Monaco Place",
    "Country": "Botswana",
    "City": "Rivera",
    "Region": "South Carolina",
    "PostalCode": 50090886
  },
  {
    "CompanyName": "Gleamink Baluba",
    "ContactName": "Murphy",
    "ContactTitle": "Mr.",
    "EmergencyMobile": 9123944215,
    "Phone": 218997789,
    "Enabled": true,
    "Fax": "Fax-86464",
    "Address": "Clermont Avenue",
    "Country": "Mauritania",
    "City": "Vicksburg",
    "Region": "Vermont",
    "PostalCode": 81780258
  },
  {
    "CompanyName": "Otherway Isotronic",
    "ContactName": "Mccall",
    "ContactTitle": "Mr.",
    "EmergencyMobile": 9124784954,
    "Phone": 213132356,
    "Enabled": true,
    "Fax": "Fax-91128",
    "Address": "Howard Place",
    "Country": "Zaire",
    "City": "Newcastle",
    "Region": "Wyoming",
    "PostalCode": 35890933
  },
  {
    "CompanyName": "Eternis Surelogic",
    "ContactName": "Villarreal",
    "ContactTitle": "Mr.",
    "EmergencyMobile": 912365740,
    "Phone": 218716630,
    "Enabled": true,
    "Fax": "Fax-28941",
    "Address": "Troutman Street",
    "Country": "Bermuda",
    "City": "Woodruff",
    "Region": "Alaska",
    "PostalCode": 44189613
  },
  {
    "CompanyName": "Euron Zogak",
    "ContactName": "Ryan",
    "ContactTitle": "Mr.",
    "EmergencyMobile": 9126468850,
    "Phone": 219515368,
    "Enabled": true,
    "Fax": "Fax-97833",
    "Address": "Whitwell Place",
    "Country": "Afghanistan",
    "City": "Camino",
    "Region": "Wisconsin",
    "PostalCode": 2150859
  },
  {
    "CompanyName": "Digifad Isosphere",
    "ContactName": "Combs",
    "ContactTitle": "Mr.",
    "EmergencyMobile": 9128400884,
    "Phone": 218938041,
    "Enabled": true,
    "Fax": "Fax-94873",
    "Address": "Lawn Court",
    "Country": "Yemen",
    "City": "Fairview",
    "Region": "Nevada",
    "PostalCode": 62570609
  },
  {
    "CompanyName": "Gynko Uxmox",
    "ContactName": "Weber",
    "ContactTitle": "Mr.",
    "EmergencyMobile": 9126188243,
    "Phone": 217339752,
    "Enabled": true,
    "Fax": "Fax-34005",
    "Address": "Hooper Street",
    "Country": "Cuba",
    "City": "Tonopah",
    "Region": "New Jersey",
    "PostalCode": 28732127
  },
  {
    "CompanyName": "Polaria Handshake",
    "ContactName": "Padilla",
    "ContactTitle": "Mr.",
    "EmergencyMobile": 9128869381,
    "Phone": 21346427,
    "Enabled": true,
    "Fax": "Fax-38437",
    "Address": "Story Street",
    "Country": "Mauritius",
    "City": "Chicopee",
    "Region": "Oklahoma",
    "PostalCode": 28305176
  },
  {
    "CompanyName": "Pyramax Earthmark",
    "ContactName": "Kidd",
    "ContactTitle": "Mr.",
    "EmergencyMobile": 9126794978,
    "Phone": 219643774,
    "Enabled": true,
    "Fax": "Fax-23157",
    "Address": "Kensington Street",
    "Country": "Congo",
    "City": "Dawn",
    "Region": "North Carolina",
    "PostalCode": 37602365
  },
  {
    "CompanyName": "Flyboyz Gonkle",
    "ContactName": "Weiss",
    "ContactTitle": "Mr.",
    "EmergencyMobile": 9126681657,
    "Phone": 217717956,
    "Enabled": true,
    "Fax": "Fax-42837",
    "Address": "Johnson Avenue",
    "Country": "Anguilla",
    "City": "Chase",
    "Region": "California",
    "PostalCode": 53396132
  },
  {
    "CompanyName": "Geekosis Imageflow",
    "ContactName": "Whitney",
    "ContactTitle": "Mr.",
    "EmergencyMobile": 912510179,
    "Phone": 216893765,
    "Enabled": true,
    "Fax": "Fax-94721",
    "Address": "Foster Avenue",
    "Country": "France",
    "City": "Sussex",
    "Region": "Mississippi",
    "PostalCode": 77045964
  },
  {
    "CompanyName": "Organica Zanity",
    "ContactName": "Pate",
    "ContactTitle": "Mr.",
    "EmergencyMobile": 9129161311,
    "Phone": 216319644,
    "Enabled": true,
    "Fax": "Fax-12831",
    "Address": "Lawrence Avenue",
    "Country": "Finland",
    "City": "Cutter",
    "Region": "Hawaii",
    "PostalCode": 68135140
  },
  {
    "CompanyName": "Typhonica Geeketron",
    "ContactName": "Gamble",
    "ContactTitle": "Mr.",
    "EmergencyMobile": 9122365474,
    "Phone": 219350564,
    "Enabled": true,
    "Fax": "Fax-74230",
    "Address": "Irving Street",
    "Country": "Canada",
    "City": "Groveville",
    "Region": "Texas",
    "PostalCode": 56662704
  },
  {
    "CompanyName": "Idego Eventage",
    "ContactName": "Duke",
    "ContactTitle": "Mr.",
    "EmergencyMobile": 9124915398,
    "Phone": 214433041,
    "Enabled": true,
    "Fax": "Fax-90958",
    "Address": "Nostrand Avenue",
    "Country": "Chad",
    "City": "Grayhawk",
    "Region": "Virgin Islands",
    "PostalCode": 94808671
  }
]